{"version": 0.6, "generator": "Overpass API 0.7.57 93a4d346", "osm3s": {"timestamp_osm_base": "2022-05-16T19:18:38Z", "copyright": "The data included in this document is from www.openstreetmap.org. The data is made available under ODbL."}, "elements": [{"type": "node", "id": 696004179, "lat": 59.514185, "lon": -1.6477408}, {"type": "node", "id": 696004184, "lat": 59.5151976, "lon": -1.6471521}, {"type": "node", "id": 696004185, "lat": 59.5151537, "lon": -1.6471151}, {"type": "node", "id": 696004189, "lat": 59.5150499, "lon": -1.6457776}, {"type": "node", "id": 696004192, "lat": 59.5153606, "lon": -1.6444422}, {"type": "node", "id": 696004193, "lat": 59.5165365, "lon": -1.6427413}, {"type": "node", "id": 696004196, "lat": 59.5166334, "lon": -1.6425189}, {"type": "node", "id": 696004198, "lat": 59.5168594, "lon": -1.6412478}, {"type": "node", "id": 696004202, "lat": 59.5171181, "lon": -1.6408351}, {"type": "node", "id": 696004206, "lat": 59.5174895, "lon": -1.640516}, {"type": "node", "id": 696004210, "lat": 59.5177998, "lon": -1.6408587}, {"type": "node", "id": 696004212, "lat": 59.5188035, "lon": -1.6402474}, {"type": "node", "id": 696004215, "lat": 59.5188973, "lon": -1.6401781}, {"type": "node", "id": 696004216, "lat": 59.5189442, "lon": -1.6401481}, {"type": "node", "id": 696004219, "lat": 59.5197596, "lon": -1.6402887}, {"type": "node", "id": 696004221, "lat": 59.520182, "lon": -1.6400513}, {"type": "node", "id": 696004225, "lat": 59.5217413, "lon": -1.6379265}, {"type": "node", "id": 696004227, "lat": 59.5225866, "lon": -1.6366696}, {"type": "node", "id": 696004232, "lat": 59.5230353, "lon": -1.6353784}, {"type": "node", "id": 696004235, "lat": 59.5231057, "lon": -1.6346795}, {"type": "node", "id": 696004238, "lat": 59.5231715, "lon": -1.6340232}, {"type": "node", "id": 696004240, "lat": 59.5237129, "lon": -1.6334251}, {"type": "node", "id": 696004242, "lat": 59.5238517, "lon": -1.633374}, {"type": "node", "id": 696004246, "lat": 59.5241945, "lon": -1.6336611}, {"type": "node", "id": 696004267, "lat": 59.5245304, "lon": -1.6344658}, {"type": "node", "id": 696004271, "lat": 59.5249061, "lon": -1.6347907}, {"type": "node", "id": 696004275, "lat": 59.5250525, "lon": -1.6348114}, {"type": "node", "id": 696005861, "lat": 59.5152529, "lon": -1.6471379}, {"type": "node", "id": 696005864, "lat": 59.5164364, "lon": -1.6464476}, {"type": "node", "id": 696005866, "lat": 59.517389, "lon": -1.6460222}, {"type": "node", "id": 696005869, "lat": 59.5181718, "lon": -1.6451713}, {"type": "node", "id": 696005872, "lat": 59.5190138, "lon": -1.6443273}, {"type": "node", "id": 696005877, "lat": 59.5199814, "lon": -1.6443158}, {"type": "node", "id": 696005882, "lat": 59.5201187, "lon": -1.6442357}, {"type": "node", "id": 696005886, "lat": 59.5206183, "lon": -1.6435468}, {"type": "node", "id": 696005890, "lat": 59.5207183, "lon": -1.6435511}, {"type": "node", "id": 696005893, "lat": 59.5211535, "lon": -1.6440112}, {"type": "node", "id": 696005895, "lat": 59.5216096, "lon": -1.6436227}, {"type": "node", "id": 696005898, "lat": 59.52186, "lon": -1.6429959}, {"type": "node", "id": 696005900, "lat": 59.5218623, "lon": -1.6425471}, {"type": "node", "id": 696005902, "lat": 59.5219163, "lon": -1.6423001}, {"type": "node", "id": 696005905, "lat": 59.5227795, "lon": -1.6413718}, {"type": "node", "id": 696005907, "lat": 59.5234527, "lon": -1.640055}, {"type": "node", "id": 696005909, "lat": 59.5237868, "lon": -1.6394206}, {"type": "node", "id": 696005917, "lat": 59.524184, "lon": -1.6386687}, {"type": "node", "id": 696005920, "lat": 59.5241562, "lon": -1.6384207}, {"type": "node", "id": 696005925, "lat": 59.5241624, "lon": -1.6377495}, {"type": "node", "id": 696005929, "lat": 59.5242844, "lon": -1.6369553}, {"type": "node", "id": 696005932, "lat": 59.5249919, "lon": -1.6349633}, {"type": "node", "id": 696005936, "lat": 59.5255223, "lon": -1.6340152}, {"type": "node", "id": 696005940, "lat": 59.5262369, "lon": -1.6333205}, {"type": "node", "id": 696005943, "lat": 59.5271635, "lon": -1.6320788}, {"type": "node", "id": 696005946, "lat": 59.5274559, "lon": -1.6312784}, {"type": "node", "id": 696005950, "lat": 59.5276112, "lon": -1.6310262}, {"type": "node", "id": 696005954, "lat": 59.5302566, "lon": -1.626691}, {"type": "node", "id": 696005962, "lat": 59.5312577, "lon": -1.6267849}, {"type": "node", "id": 696005969, "lat": 59.5315424, "lon": -1.6272029}, {"type": "node", "id": 696005976, "lat": 59.5323813, "lon": -1.6292481}, {"type": "node", "id": 696005980, "lat": 59.532624, "lon": -1.6293553}, {"type": "node", "id": 696005982, "lat": 59.5326875, "lon": -1.6292272}, {"type": "node", "id": 696005986, "lat": 59.5329595, "lon": -1.6288771}, {"type": "node", "id": 696005990, "lat": 59.5333088, "lon": -1.6291564}, {"type": "node", "id": 696005993, "lat": 59.5335854, "lon": -1.6290983}, {"type": "node", "id": 696007399, "lat": 59.531563, "lon": -1.6258715}, {"type": "node", "id": 696007402, "lat": 59.5316616, "lon": -1.6249948}, {"type": "node", "id": 696007404, "lat": 59.5319587, "lon": -1.6243398}, {"type": "node", "id": 696007405, "lat": 59.5325954, "lon": -1.6233518}, {"type": "node", "id": 696007407, "lat": 59.5327026, "lon": -1.6225383}, {"type": "node", "id": 696007410, "lat": 59.5330878, "lon": -1.6193277}, {"type": "node", "id": 696007412, "lat": 59.5336862, "lon": -1.6180335}, {"type": "node", "id": 696007414, "lat": 59.5339481, "lon": -1.617848}, {"type": "node", "id": 696007416, "lat": 59.5346201, "lon": -1.6178176}, {"type": "node", "id": 696007419, "lat": 59.5347863, "lon": -1.6175394}, {"type": "node", "id": 696007422, "lat": 59.5350253, "lon": -1.6157391}, {"type": "node", "id": 696007424, "lat": 59.535185, "lon": -1.6139079}, {"type": "node", "id": 696007427, "lat": 59.5352328, "lon": -1.6133482}, {"type": "node", "id": 696007430, "lat": 59.5351403, "lon": -1.6125781}, {"type": "node", "id": 696007433, "lat": 59.5351494, "lon": -1.6115734}, {"type": "node", "id": 696007436, "lat": 59.5354946, "lon": -1.6106294}, {"type": "node", "id": 696007438, "lat": 59.5369157, "lon": -1.6094746}, {"type": "node", "id": 696007442, "lat": 59.537234, "lon": -1.6094185}, {"type": "node", "id": 696007443, "lat": 59.5374248, "lon": -1.609574}, {"type": "node", "id": 696007452, "lat": 59.5388608, "lon": -1.6148526}, {"type": "node", "id": 696007454, "lat": 59.5391296, "lon": -1.6153336}, {"type": "node", "id": 696007457, "lat": 59.5395879, "lon": -1.6153988}, {"type": "node", "id": 696007459, "lat": 59.540015, "lon": -1.6148752}, {"type": "node", "id": 696007462, "lat": 59.5402881, "lon": -1.6144133}, {"type": "node", "id": 696007465, "lat": 59.5415175, "lon": -1.6134514}, {"type": "node", "id": 696007468, "lat": 59.5423957, "lon": -1.6136308}, {"type": "node", "id": 696007473, "lat": 59.5438787, "lon": -1.6127431}, {"type": "node", "id": 696007476, "lat": 59.5441441, "lon": -1.6121088}, {"type": "node", "id": 696007478, "lat": 59.5443783, "lon": -1.6120138}, {"type": "node", "id": 696007481, "lat": 59.5460069, "lon": -1.6128607}, {"type": "node", "id": 696007483, "lat": 59.5464663, "lon": -1.6134017}, {"type": "node", "id": 696007485, "lat": 59.5472975, "lon": -1.6146856}, {"type": "node", "id": 696007487, "lat": 59.5479856, "lon": -1.6155039}, {"type": "node", "id": 696007490, "lat": 59.5483025, "lon": -1.6155797}, {"type": "node", "id": 696007493, "lat": 59.5485562, "lon": -1.614999}, {"type": "node", "id": 696007496, "lat": 59.5485273, "lon": -1.6142631}, {"type": "node", "id": 696007498, "lat": 59.5482969, "lon": -1.611243}, {"type": "node", "id": 696007503, "lat": 59.5483061, "lon": -1.6111291}, {"type": "node", "id": 696007505, "lat": 59.5497436, "lon": -1.6092879}, {"type": "node", "id": 696007507, "lat": 59.5501722, "lon": -1.6091315}, {"type": "node", "id": 696007509, "lat": 59.5507272, "lon": -1.6100061}, {"type": "node", "id": 696007512, "lat": 59.5511954, "lon": -1.6108135}, {"type": "node", "id": 696007514, "lat": 59.5512765, "lon": -1.6108672}, {"type": "node", "id": 696007517, "lat": 59.5515778, "lon": -1.610713}, {"type": "node", "id": 696007520, "lat": 59.5516117, "lon": -1.6106468}, {"type": "node", "id": 696007842, "lat": 59.5376012, "lon": -1.6036649}, {"type": "node", "id": 696007845, "lat": 59.5374129, "lon": -1.6038449}, {"type": "node", "id": 696007849, "lat": 59.537203, "lon": -1.6042499}, {"type": "node", "id": 696007853, "lat": 59.5372208, "lon": -1.6057581}, {"type": "node", "id": 696007856, "lat": 59.5371759, "lon": -1.6069077}, {"type": "node", "id": 696007859, "lat": 59.536968, "lon": -1.6076724}, {"type": "node", "id": 696007863, "lat": 59.5367167, "lon": -1.6081042}, {"type": "node", "id": 696007866, "lat": 59.5363603, "lon": -1.6085629}, {"type": "node", "id": 696007870, "lat": 59.5360614, "lon": -1.6096369}, {"type": "node", "id": 696007873, "lat": 59.5357993, "lon": -1.610066}, {"type": "node", "id": 893419435, "lat": 59.5203663, "lon": -1.6422923}, {"type": "node", "id": 893419437, "lat": 59.5204493, "lon": -1.6427889}, {"type": "node", "id": 893419595, "lat": 59.5196657, "lon": -1.6391411}, {"type": "node", "id": 893419596, "lat": 59.5200575, "lon": -1.6399272}, {"type": "node", "id": 893419598, "lat": 59.5202594, "lon": -1.6399306}, {"type": "node", "id": 893419839, "lat": 59.5214942, "lon": -1.6370383}, {"type": "node", "id": 893420882, "lat": 59.5263106, "lon": -1.6305915}, {"type": "node", "id": 893420886, "lat": 59.5268007, "lon": -1.6327438}, {"type": "node", "id": 893422146, "lat": 59.5444618, "lon": -1.6285889}, {"type": "node", "id": 893422148, "lat": 59.5442116, "lon": -1.6280689}, {"type": "node", "id": 893422152, "lat": 59.5436049, "lon": -1.6279231}, {"type": "node", "id": 893422154, "lat": 59.5433003, "lon": -1.627495}, {"type": "node", "id": 893422157, "lat": 59.5431369, "lon": -1.627505}, {"type": "node", "id": 893422159, "lat": 59.5427279, "lon": -1.6273118}, {"type": "node", "id": 893422160, "lat": 59.5420564, "lon": -1.627306}, {"type": "node", "id": 893422162, "lat": 59.5417643, "lon": -1.6277042}, {"type": "node", "id": 893422165, "lat": 59.5413376, "lon": -1.6277955}, {"type": "node", "id": 893422169, "lat": 59.5411082, "lon": -1.6281826}, {"type": "node", "id": 893422170, "lat": 59.5407182, "lon": -1.6282813}, {"type": "node", "id": 893422172, "lat": 59.5399312, "lon": -1.6289934}, {"type": "node", "id": 893422173, "lat": 59.5395562, "lon": -1.6290989}, {"type": "node", "id": 893422175, "lat": 59.5390235, "lon": -1.6288326}, {"type": "node", "id": 893422177, "lat": 59.5389035, "lon": -1.6286054}, {"type": "node", "id": 893422179, "lat": 59.5387647, "lon": -1.6287232}, {"type": "node", "id": 893422181, "lat": 59.5385861, "lon": -1.6296217}, {"type": "node", "id": 893422183, "lat": 59.5384467, "lon": -1.6296826}, {"type": "node", "id": 893422185, "lat": 59.5378488, "lon": -1.6288317}, {"type": "node", "id": 893422188, "lat": 59.5374575, "lon": -1.6286232}, {"type": "node", "id": 893422189, "lat": 59.5369976, "lon": -1.6278563}, {"type": "node", "id": 893422190, "lat": 59.536866, "lon": -1.6277637}, {"type": "node", "id": 893422191, "lat": 59.5366697, "lon": -1.6278709}, {"type": "node", "id": 893422192, "lat": 59.5365665, "lon": -1.6282303}, {"type": "node", "id": 893422194, "lat": 59.5352004, "lon": -1.6286397}, {"type": "node", "id": 893422196, "lat": 59.5337744, "lon": -1.6325497}, {"type": "node", "id": 893422197, "lat": 59.533562, "lon": -1.6327253}, {"type": "node", "id": 893422199, "lat": 59.533342, "lon": -1.6324017}, {"type": "node", "id": 893422201, "lat": 59.5333892, "lon": -1.6319374}, {"type": "node", "id": 893422202, "lat": 59.5340862, "lon": -1.6294141}, {"type": "node", "id": 893422204, "lat": 59.5340654, "lon": -1.6292477}, {"type": "node", "id": 893422274, "lat": 59.5485836, "lon": -1.6290989}, {"type": "node", "id": 893422277, "lat": 59.548551, "lon": -1.6289058}, {"type": "node", "id": 893422280, "lat": 59.5485619, "lon": -1.6279831}, {"type": "node", "id": 893422283, "lat": 59.5484096, "lon": -1.6272536}, {"type": "node", "id": 893422285, "lat": 59.5482682, "lon": -1.6268459}, {"type": "node", "id": 893422287, "lat": 59.5478876, "lon": -1.6262236}, {"type": "node", "id": 893422288, "lat": 59.5475613, "lon": -1.6260305}, {"type": "node", "id": 893422289, "lat": 59.5472025, "lon": -1.6254726}, {"type": "node", "id": 893422290, "lat": 59.5466009, "lon": -1.6252706}, {"type": "node", "id": 893422291, "lat": 59.545882, "lon": -1.6265563}, {"type": "node", "id": 893422292, "lat": 59.5456839, "lon": -1.6267741}, {"type": "node", "id": 893422294, "lat": 59.5454301, "lon": -1.6270146}, {"type": "node", "id": 893422296, "lat": 59.5450939, "lon": -1.6277062}, {"type": "node", "id": 893422297, "lat": 59.5447361, "lon": -1.6279834}, {"type": "node", "id": 893422351, "lat": 59.5363913, "lon": -1.6093874}, {"type": "node", "id": 893422484, "lat": 59.5358531, "lon": -1.6103062}, {"type": "node", "id": 893422627, "lat": 59.5362424, "lon": -1.6090123}, {"type": "node", "id": 893423540, "lat": 59.5137666, "lon": -1.6522916}, {"type": "node", "id": 893423541, "lat": 59.5139781, "lon": -1.6515896}, {"type": "node", "id": 893423542, "lat": 59.5143325, "lon": -1.6511471}, {"type": "node", "id": 893423543, "lat": 59.5143897, "lon": -1.6509405}, {"type": "node", "id": 893423545, "lat": 59.5144342, "lon": -1.6504952}, {"type": "node", "id": 893423550, "lat": 59.514351, "lon": -1.6500089}, {"type": "node", "id": 893423554, "lat": 59.5141469, "lon": -1.6491404}, {"type": "node", "id": 893423560, "lat": 59.5140428, "lon": -1.6478703}, {"type": "node", "id": 1066047528, "lat": 59.5375919, "lon": -1.6287536}, {"type": "node", "id": 1066047542, "lat": 59.5387991, "lon": -1.6286215}, {"type": "node", "id": 1066047544, "lat": 59.5352525, "lon": -1.6285825}, {"type": "node", "id": 1066047548, "lat": 59.5390592, "lon": -1.6288728}, {"type": "node", "id": 1066047565, "lat": 59.528516, "lon": -1.6305442}, {"type": "node", "id": 1066047566, "lat": 59.5388735, "lon": -1.6285912}, {"type": "node", "id": 1066047567, "lat": 59.5318986, "lon": -1.6302975}, {"type": "node", "id": 1066047568, "lat": 59.5452769, "lon": -1.6272675}, {"type": "node", "id": 1066047569, "lat": 59.5340112, "lon": -1.6290216}, {"type": "node", "id": 1066047571, "lat": 59.5410166, "lon": -1.628288}, {"type": "node", "id": 1066047572, "lat": 59.5289628, "lon": -1.6288504}, {"type": "node", "id": 1066047575, "lat": 59.528691, "lon": -1.6292707}, {"type": "node", "id": 1066047601, "lat": 59.5305471, "lon": -1.6266053}, {"type": "node", "id": 1066047603, "lat": 59.5373527, "lon": -1.6284337}, {"type": "node", "id": 1066047608, "lat": 59.5443981, "lon": -1.6284472}, {"type": "node", "id": 1066047609, "lat": 59.5290043, "lon": -1.6288813}, {"type": "node", "id": 1066047613, "lat": 59.531904, "lon": -1.6306676}, {"type": "node", "id": 1066047615, "lat": 59.5383831, "lon": -1.629647}, {"type": "node", "id": 1066047647, "lat": 59.5286357, "lon": -1.630842}, {"type": "node", "id": 1066047651, "lat": 59.5386489, "lon": -1.6292159}, {"type": "node", "id": 1066047661, "lat": 59.5272777, "lon": -1.6317298}, {"type": "node", "id": 1066047688, "lat": 59.5290065, "lon": -1.6287793, "tags": {"barrier": "cattle_grid"}}, {"type": "node", "id": 1066047692, "lat": 59.5354414, "lon": -1.6285574}, {"type": "node", "id": 1066047697, "lat": 59.5315967, "lon": -1.6289778}, {"type": "node", "id": 1066047704, "lat": 59.5386069, "lon": -1.6295706}, {"type": "node", "id": 1066047726, "lat": 59.5333423, "lon": -1.6321717}, {"type": "node", "id": 1066047732, "lat": 59.5283488, "lon": -1.6298345}, {"type": "node", "id": 1066047752, "lat": 59.5378992, "lon": -1.6288987}, {"type": "node", "id": 1066047785, "lat": 59.5436811, "lon": -1.6279905}, {"type": "node", "id": 1066047786, "lat": 59.5447044, "lon": -1.6280348}, {"type": "node", "id": 1066047790, "lat": 59.5355944, "lon": -1.6285448}, {"type": "node", "id": 1066047816, "lat": 59.5375275, "lon": -1.6287198}, {"type": "node", "id": 1066047818, "lat": 59.5446666, "lon": -1.6282338}, {"type": "node", "id": 1066047819, "lat": 59.5414745, "lon": -1.6277923}, {"type": "node", "id": 1066047834, "lat": 59.5385244, "lon": -1.6296908}, {"type": "node", "id": 1066047839, "lat": 59.5318211, "lon": -1.6299139}, {"type": "node", "id": 1066047842, "lat": 59.5336438, "lon": -1.6327376}, {"type": "node", "id": 1066047843, "lat": 59.5367264, "lon": -1.6277843}, {"type": "node", "id": 1066047846, "lat": 59.5436255, "lon": -1.6279559}, {"type": "node", "id": 1066047850, "lat": 59.5333853, "lon": -1.6291761}, {"type": "node", "id": 1066047866, "lat": 59.5340237, "lon": -1.6298045}, {"type": "node", "id": 1066047872, "lat": 59.5378038, "lon": -1.6287964}, {"type": "node", "id": 1066047891, "lat": 59.5336952, "lon": -1.6326974}, {"type": "node", "id": 1066047902, "lat": 59.5349855, "lon": -1.6290772}, {"type": "node", "id": 1066047920, "lat": 59.5424833, "lon": -1.6273275}, {"type": "node", "id": 1066047922, "lat": 59.5416571, "lon": -1.6278223}, {"type": "node", "id": 1066047925, "lat": 59.5340904, "lon": -1.6295353}, {"type": "node", "id": 1066047927, "lat": 59.5444336, "lon": -1.6285532}, {"type": "node", "id": 1066047930, "lat": 59.5342764, "lon": -1.6310081}, {"type": "node", "id": 1066047944, "lat": 59.5333371, "lon": -1.6323032}, {"type": "node", "id": 1066047958, "lat": 59.5314655, "lon": -1.6270609}, {"type": "node", "id": 1066047959, "lat": 59.5433811, "lon": -1.6275316}, {"type": "node", "id": 1066047967, "lat": 59.5442597, "lon": -1.6280821}, {"type": "node", "id": 1066047969, "lat": 59.5353193, "lon": -1.6285624}, {"type": "node", "id": 1066047972, "lat": 59.5442884, "lon": -1.6281164}, {"type": "node", "id": 1066047974, "lat": 59.5344707, "lon": -1.6306018}, {"type": "node", "id": 1066047978, "lat": 59.5372001, "lon": -1.6281984}, {"type": "node", "id": 1066047983, "lat": 59.5370687, "lon": -1.6279692}, {"type": "node", "id": 1066047985, "lat": 59.533358, "lon": -1.6320607}, {"type": "node", "id": 1066047987, "lat": 59.5426444, "lon": -1.6273257}, {"type": "node", "id": 1066048008, "lat": 59.5437057, "lon": -1.6280006}, {"type": "node", "id": 1066048010, "lat": 59.5428401, "lon": -1.6273239}, {"type": "node", "id": 1066048012, "lat": 59.5365918, "lon": -1.6281751}, {"type": "node", "id": 1066048015, "lat": 59.5406156, "lon": -1.628403}, {"type": "node", "id": 1066048018, "lat": 59.5312119, "lon": -1.6267707}, {"type": "node", "id": 1066048019, "lat": 59.539463, "lon": -1.6290764}, {"type": "node", "id": 1066048039, "lat": 59.5347718, "lon": -1.6297018}, {"type": "node", "id": 1066048041, "lat": 59.5449203, "lon": -1.6278653}, {"type": "node", "id": 1066048043, "lat": 59.5391087, "lon": -1.628906}, {"type": "node", "id": 1066048050, "lat": 59.5339664, "lon": -1.6289209}, {"type": "node", "id": 1066048075, "lat": 59.5324546, "lon": -1.6293675}, {"type": "node", "id": 1066048076, "lat": 59.5431707, "lon": -1.6275046}, {"type": "node", "id": 1066048078, "lat": 59.5318401, "lon": -1.6309868}, {"type": "node", "id": 1066048079, "lat": 59.5435148, "lon": -1.6276931}, {"type": "node", "id": 1066048084, "lat": 59.5359498, "lon": -1.6284631}, {"type": "node", "id": 1066048109, "lat": 59.5337402, "lon": -1.6326267}, {"type": "node", "id": 1066048110, "lat": 59.5425763, "lon": -1.6273323}, {"type": "node", "id": 1066048112, "lat": 59.5327768, "lon": -1.6290513}, {"type": "node", "id": 1066048117, "lat": 59.5285691, "lon": -1.6306998}, {"type": "node", "id": 1066048119, "lat": 59.5337293, "lon": -1.6290335}, {"type": "node", "id": 1066048121, "lat": 59.5338066, "lon": -1.6305619}, {"type": "node", "id": 1066048126, "lat": 59.5461302, "lon": -1.6259735}, {"type": "node", "id": 1066048143, "lat": 59.5377507, "lon": -1.6287637}, {"type": "node", "id": 1066048147, "lat": 59.5451674, "lon": -1.6275536}, {"type": "node", "id": 1066048149, "lat": 59.5434474, "lon": -1.6275867}, {"type": "node", "id": 1066048155, "lat": 59.5330331, "lon": -1.6288594}, {"type": "node", "id": 1066048157, "lat": 59.5314715, "lon": -1.6310673}, {"type": "node", "id": 1066048160, "lat": 59.5366494, "lon": -1.62793}, {"type": "node", "id": 1066048189, "lat": 59.5376743, "lon": -1.6287509}, {"type": "node", "id": 1066048194, "lat": 59.5317435, "lon": -1.6310217}, {"type": "node", "id": 1066048199, "lat": 59.5454106, "lon": -1.6270489}, {"type": "node", "id": 1066048206, "lat": 59.5317191, "lon": -1.6295518}, {"type": "node", "id": 1066048212, "lat": 59.5334292, "lon": -1.6325916}, {"type": "node", "id": 1066048217, "lat": 59.5316402, "lon": -1.6286774}, {"type": "node", "id": 1066048219, "lat": 59.546478, "lon": -1.6253501}, {"type": "node", "id": 1066048242, "lat": 59.53187, "lon": -1.6309412}, {"type": "node", "id": 1066048250, "lat": 59.5318285, "lon": -1.6279794}, {"type": "node", "id": 1066048253, "lat": 59.54055, "lon": -1.628476}, {"type": "node", "id": 1066048292, "lat": 59.5319081, "lon": -1.6304155}, {"type": "node", "id": 1066048300, "lat": 59.5287744, "lon": -1.6312309}, {"type": "node", "id": 1066048304, "lat": 59.5429172, "lon": -1.6273541}, {"type": "node", "id": 1066048307, "lat": 59.5444983, "lon": -1.6286506}, {"type": "node", "id": 1066048310, "lat": 59.5318088, "lon": -1.6310136}, {"type": "node", "id": 1066048333, "lat": 59.5445168, "lon": -1.628568}, {"type": "node", "id": 1066048338, "lat": 59.5406714, "lon": -1.6283211}, {"type": "node", "id": 1066048346, "lat": 59.5290356, "lon": -1.6288384, "tags": {"barrier": "gate"}}, {"type": "node", "id": 1066048350, "lat": 59.5445509, "lon": -1.6285369}, {"type": "node", "id": 1066048354, "lat": 59.5383346, "lon": -1.6296099}, {"type": "node", "id": 1066048357, "lat": 59.5325686, "lon": -1.629402}, {"type": "node", "id": 1066048360, "lat": 59.538494, "lon": -1.629693}, {"type": "node", "id": 1066048380, "lat": 59.5389598, "lon": -1.628691}, {"type": "node", "id": 1066048389, "lat": 59.5287282, "lon": -1.631078}, {"type": "node", "id": 1066048395, "lat": 59.5316783, "lon": -1.630909}, {"type": "node", "id": 1066048398, "lat": 59.544531, "lon": -1.6287498}, {"type": "node", "id": 1066048401, "lat": 59.5318904, "lon": -1.630842}, {"type": "node", "id": 1066048410, "lat": 59.5317286, "lon": -1.6309922}, {"type": "node", "id": 1066048415, "lat": 59.531885, "lon": -1.6308956}, {"type": "node", "id": 1066048421, "lat": 59.5412843, "lon": -1.6278453}, {"type": "node", "id": 1066048430, "lat": 59.5336057, "lon": -1.632747}, {"type": "node", "id": 1066048435, "lat": 59.5409554, "lon": -1.6282991}, {"type": "node", "id": 1066048438, "lat": 59.5279503, "lon": -1.6304687}, {"type": "node", "id": 1066048443, "lat": 59.5389388, "lon": -1.6286415}, {"type": "node", "id": 1066048445, "lat": 59.5317068, "lon": -1.6309305}, {"type": "node", "id": 1066048465, "lat": 59.5328841, "lon": -1.6289371}, {"type": "node", "id": 1066048466, "lat": 59.5340414, "lon": -1.6291346}, {"type": "node", "id": 1066048468, "lat": 59.5429656, "lon": -1.6273893}, {"type": "node", "id": 1066048474, "lat": 59.5273521, "lon": -1.631493}, {"type": "node", "id": 1066048478, "lat": 59.5331378, "lon": -1.6289334}, {"type": "node", "id": 1066048492, "lat": 59.5316062, "lon": -1.6287954}, {"type": "node", "id": 1066048495, "lat": 59.5445554, "lon": -1.6288598}, {"type": "node", "id": 1066048501, "lat": 59.5386268, "lon": -1.629468}, {"type": "node", "id": 1066048502, "lat": 59.5453531, "lon": -1.6271279}, {"type": "node", "id": 1066048516, "lat": 59.5365146, "lon": -1.6282834}, {"type": "node", "id": 1066048519, "lat": 59.5417115, "lon": -1.627786}, {"type": "node", "id": 1066048525, "lat": 59.5385559, "lon": -1.6296702}, {"type": "node", "id": 1066048528, "lat": 59.5423757, "lon": -1.6273039}, {"type": "node", "id": 1066048536, "lat": 59.5317735, "lon": -1.631027}, {"type": "node", "id": 1066048558, "lat": 59.5389836, "lon": -1.6287563}, {"type": "node", "id": 1066048562, "lat": 59.5332285, "lon": -1.6290891}, {"type": "node", "id": 1066048565, "lat": 59.529069, "lon": -1.6286917}, {"type": "node", "id": 1066048584, "lat": 59.5325091, "lon": -1.6294061}, {"type": "node", "id": 1066048585, "lat": 59.5367855, "lon": -1.627757}, {"type": "node", "id": 1066048589, "lat": 59.5446112, "lon": -1.6284063}, {"type": "node", "id": 1066048592, "lat": 59.5412247, "lon": -1.6279452}, {"type": "node", "id": 1066048611, "lat": 59.533573, "lon": -1.6313442}, {"type": "node", "id": 1066048618, "lat": 59.5290574, "lon": -1.6287874}, {"type": "node", "id": 1066048620, "lat": 59.5410642, "lon": -1.6282552}, {"type": "node", "id": 1066048622, "lat": 59.5388382, "lon": -1.6285925}, {"type": "node", "id": 1066048644, "lat": 59.5317422, "lon": -1.6284226}, {"type": "node", "id": 1066048653, "lat": 59.5450383, "lon": -1.6277675}, {"type": "node", "id": 1066048663, "lat": 59.5408289, "lon": -1.6282703}, {"type": "node", "id": 1066048665, "lat": 59.5345551, "lon": -1.630386}, {"type": "node", "id": 1066048671, "lat": 59.5430887, "lon": -1.6274897}, {"type": "node", "id": 1066048675, "lat": 59.5337945, "lon": -1.629}, {"type": "node", "id": 1066048677, "lat": 59.5458184, "lon": -1.6267086}, {"type": "node", "id": 1066048680, "lat": 59.5315953, "lon": -1.6288759}, {"type": "node", "id": 1066048681, "lat": 59.5364745, "lon": -1.6283185}, {"type": "node", "id": 1066048691, "lat": 59.5443049, "lon": -1.6281616}, {"type": "node", "id": 1066048692, "lat": 59.5382552, "lon": -1.629504}, {"type": "node", "id": 1066048693, "lat": 59.541607, "lon": -1.6278303}, {"type": "node", "id": 1066048697, "lat": 59.5341598, "lon": -1.631335}, {"type": "node", "id": 1066048714, "lat": 59.5350989, "lon": -1.6287913}, {"type": "node", "id": 1066048717, "lat": 59.5318809, "lon": -1.630158}, {"type": "node", "id": 1066048719, "lat": 59.5466898, "lon": -1.6252877}, {"type": "node", "id": 1066048720, "lat": 59.5401633, "lon": -1.6287711}, {"type": "node", "id": 1066048722, "lat": 59.5333692, "lon": -1.6324957}, {"type": "node", "id": 1066048726, "lat": 59.5335118, "lon": -1.6326838}, {"type": "node", "id": 1066048729, "lat": 59.5294453, "lon": -1.628057}, {"type": "node", "id": 1066048732, "lat": 59.54469, "lon": -1.6280768}, {"type": "node", "id": 1066048756, "lat": 59.5340685, "lon": -1.6296381}, {"type": "node", "id": 1066048759, "lat": 59.5465451, "lon": -1.6252871}, {"type": "node", "id": 1066048762, "lat": 59.5369489, "lon": -1.6278064}, {"type": "node", "id": 1066048766, "lat": 59.5457808, "lon": -1.6267399}, {"type": "node", "id": 1066048787, "lat": 59.5283773, "lon": -1.6299273}, {"type": "node", "id": 1066048795, "lat": 59.5455241, "lon": -1.6268691}, {"type": "node", "id": 1066048801, "lat": 59.5317789, "lon": -1.6282939}, {"type": "node", "id": 1066048804, "lat": 59.5445799, "lon": -1.628943}, {"type": "node", "id": 1066048832, "lat": 59.5460298, "lon": -1.6261731}, {"type": "node", "id": 1066048834, "lat": 59.5434963, "lon": -1.6276606}, {"type": "node", "id": 1066048838, "lat": 59.5289254, "lon": -1.6318237}, {"type": "node", "id": 1066048840, "lat": 59.5414134, "lon": -1.6277839}, {"type": "node", "id": 1066048842, "lat": 59.5421325, "lon": -1.6272986}, {"type": "node", "id": 1066048861, "lat": 59.5407705, "lon": -1.6282661}, {"type": "node", "id": 1066048867, "lat": 59.5419985, "lon": -1.6273398}, {"type": "node", "id": 1066048871, "lat": 59.5398584, "lon": -1.6290409}, {"type": "node", "id": 1066048876, "lat": 59.5269977, "lon": -1.6324298}, {"type": "node", "id": 1066094900, "lat": 59.5179934, "lon": -1.6443442}, {"type": "node", "id": 1066094903, "lat": 59.5226283, "lon": -1.6415984}, {"type": "node", "id": 1066094905, "lat": 59.521085, "lon": -1.6440309}, {"type": "node", "id": 1066094909, "lat": 59.5241895, "lon": -1.6373888}, {"type": "node", "id": 1066094924, "lat": 59.5234906, "lon": -1.639946}, {"type": "node", "id": 1066094926, "lat": 59.5218793, "lon": -1.6423882}, {"type": "node", "id": 1066094933, "lat": 59.5217119, "lon": -1.6434584}, {"type": "node", "id": 1066094936, "lat": 59.5244622, "lon": -1.6363889}, {"type": "node", "id": 1066094944, "lat": 59.5150757, "lon": -1.6472131}, {"type": "node", "id": 1066094947, "lat": 59.5245155, "lon": -1.6370915}, {"type": "node", "id": 1066094949, "lat": 59.5265079, "lon": -1.6330478}, {"type": "node", "id": 1066094954, "lat": 59.5200578, "lon": -1.6442789}, {"type": "node", "id": 1066094961, "lat": 59.5174885, "lon": -1.6459057}, {"type": "node", "id": 1066094976, "lat": 59.5217947, "lon": -1.6432649}, {"type": "node", "id": 1066094977, "lat": 59.5162896, "lon": -1.6465486}, {"type": "node", "id": 1066094979, "lat": 59.5207704, "lon": -1.6436042}, {"type": "node", "id": 1066094981, "lat": 59.5214973, "lon": -1.6437581}, {"type": "node", "id": 1066095001, "lat": 59.5195506, "lon": -1.6443768}, {"type": "node", "id": 1066095005, "lat": 59.5160511, "lon": -1.6467095}, {"type": "node", "id": 1066095009, "lat": 59.5140542, "lon": -1.6479755}, {"type": "node", "id": 1066095012, "lat": 59.5209572, "lon": -1.6439112}, {"type": "node", "id": 1066095020, "lat": 59.5197533, "lon": -1.6443531}, {"type": "node", "id": 1066095022, "lat": 59.5241781, "lon": -1.63874}, {"type": "node", "id": 1066095026, "lat": 59.5173465, "lon": -1.6460655}, {"type": "node", "id": 1066095028, "lat": 59.524665, "lon": -1.6357461}, {"type": "node", "id": 1066095029, "lat": 59.5191736, "lon": -1.6443135}, {"type": "node", "id": 1066095041, "lat": 59.5233769, "lon": -1.6402671}, {"type": "node", "id": 1066095042, "lat": 59.5181351, "lon": -1.6450278}, {"type": "node", "id": 1066095046, "lat": 59.5243694, "lon": -1.6366846}, {"type": "node", "id": 1066095050, "lat": 59.524245, "lon": -1.6371004}, {"type": "node", "id": 1066095064, "lat": 59.5180873, "lon": -1.6448243}, {"type": "node", "id": 1066095073, "lat": 59.5206887, "lon": -1.6435286}, {"type": "node", "id": 1066095076, "lat": 59.5218397, "lon": -1.6431254}, {"type": "node", "id": 1066095085, "lat": 59.5221138, "lon": -1.6420999}, {"type": "node", "id": 1066095087, "lat": 59.5167791, "lon": -1.6463151}, {"type": "node", "id": 1066095092, "lat": 59.5184619, "lon": -1.6447693}, {"type": "node", "id": 1066095110, "lat": 59.5204308, "lon": -1.6425632}, {"type": "node", "id": 1066095114, "lat": 59.5241343, "lon": -1.6388937}, {"type": "node", "id": 1066095117, "lat": 59.5232356, "lon": -1.640529}, {"type": "node", "id": 1066095123, "lat": 59.5178383, "lon": -1.6435503}, {"type": "node", "id": 1066095124, "lat": 59.5242136, "lon": -1.6372158}, {"type": "node", "id": 1066095129, "lat": 59.5258721, "lon": -1.6336879}, {"type": "node", "id": 1066095131, "lat": 59.5190822, "lon": -1.6443034}, {"type": "node", "id": 1066095144, "lat": 59.5151294, "lon": -1.6470645}, {"type": "node", "id": 1066095145, "lat": 59.5229336, "lon": -1.6410592}, {"type": "node", "id": 1066095146, "lat": 59.5202893, "lon": -1.6440104}, {"type": "node", "id": 1066095147, "lat": 59.5241651, "lon": -1.6388143}, {"type": "node", "id": 1066095150, "lat": 59.5172686, "lon": -1.6461138}, {"type": "node", "id": 1066095153, "lat": 59.5177993, "lon": -1.6455479}, {"type": "node", "id": 1066095154, "lat": 59.5252086, "lon": -1.6345363}, {"type": "node", "id": 1066095157, "lat": 59.5244815, "lon": -1.6368126}, {"type": "node", "id": 1066095158, "lat": 59.5244543, "lon": -1.6368823}, {"type": "node", "id": 1066095173, "lat": 59.524153, "lon": -1.638271}, {"type": "node", "id": 1066095177, "lat": 59.5247808, "lon": -1.6354208}, {"type": "node", "id": 1066095179, "lat": 59.5185497, "lon": -1.6446819}, {"type": "node", "id": 1066095188, "lat": 59.5254529, "lon": -1.634112}, {"type": "node", "id": 1066095189, "lat": 59.5150952, "lon": -1.6471766}, {"type": "node", "id": 1066095206, "lat": 59.522708, "lon": -1.6415141}, {"type": "node", "id": 1066095207, "lat": 59.5145033, "lon": -1.6475468}, {"type": "node", "id": 1066095211, "lat": 59.5151158, "lon": -1.6469831}, {"type": "node", "id": 1066095214, "lat": 59.5244679, "lon": -1.636767}, {"type": "node", "id": 1066095218, "lat": 59.5210247, "lon": -1.6440006}, {"type": "node", "id": 1066095222, "lat": 59.5151156, "lon": -1.6470881}, {"type": "node", "id": 1066095229, "lat": 59.5171475, "lon": -1.6461673}, {"type": "node", "id": 1066114972, "lat": 59.5139767, "lon": -1.6475897}, {"type": "node", "id": 1066114975, "lat": 59.5139876, "lon": -1.6476809}, {"type": "node", "id": 1066115000, "lat": 59.5139069, "lon": -1.6517}, {"type": "node", "id": 1066115072, "lat": 59.5140162, "lon": -1.6477855}, {"type": "node", "id": 1066115083, "lat": 59.5142108, "lon": -1.6513531}, {"type": "node", "id": 1066115090, "lat": 59.5143967, "lon": -1.6502154}, {"type": "node", "id": 1066115107, "lat": 59.5142338, "lon": -1.6496018}, {"type": "node", "id": 1066115130, "lat": 59.5139631, "lon": -1.6474744}, {"type": "node", "id": 1066115153, "lat": 59.5144177, "lon": -1.6507704}, {"type": "node", "id": 1066139385, "lat": 59.5171294, "lon": -1.6413348}, {"type": "node", "id": 1066139386, "lat": 59.516758, "lon": -1.6415426}, {"type": "node", "id": 1066139387, "lat": 59.5169225, "lon": -1.6411288}, {"type": "node", "id": 1066139391, "lat": 59.5151072, "lon": -1.6453839}, {"type": "node", "id": 1066139393, "lat": 59.5160926, "lon": -1.6357451}, {"type": "node", "id": 1066139394, "lat": 59.5177273, "lon": -1.640816}, {"type": "node", "id": 1066139397, "lat": 59.5173455, "lon": -1.6419326}, {"type": "node", "id": 1066139399, "lat": 59.5172737, "lon": -1.6414421}, {"type": "node", "id": 1066139401, "lat": 59.5213499, "lon": -1.6326981}, {"type": "node", "id": 1066139403, "lat": 59.5176091, "lon": -1.6406344}, {"type": "node", "id": 1066139404, "lat": 59.5167158, "lon": -1.6405998}, {"type": "node", "id": 1066139406, "lat": 59.5195513, "lon": -1.633315}, {"type": "node", "id": 1066139407, "lat": 59.519622, "lon": -1.6333954}, {"type": "node", "id": 1066139408, "lat": 59.5195755, "lon": -1.6403114}, {"type": "node", "id": 1066139409, "lat": 59.5229294, "lon": -1.6358486}, {"type": "node", "id": 1066139411, "lat": 59.5166618, "lon": -1.6424023}, {"type": "node", "id": 1066139413, "lat": 59.5199594, "lon": -1.6333257}, {"type": "node", "id": 1066139416, "lat": 59.5212954, "lon": -1.6326981}, {"type": "node", "id": 1066139420, "lat": 59.5223593, "lon": -1.6333096}, {"type": "node", "id": 1066139421, "lat": 59.5202021, "lon": -1.6399016}, {"type": "node", "id": 1066139422, "lat": 59.5194315, "lon": -1.633256}, {"type": "node", "id": 1066139423, "lat": 59.516697, "lon": -1.6420533}, {"type": "node", "id": 1066139425, "lat": 59.5184855, "lon": -1.640536}, {"type": "node", "id": 1066139426, "lat": 59.5154271, "lon": -1.6442847}, {"type": "node", "id": 1066139427, "lat": 59.5214424, "lon": -1.6327678}, {"type": "node", "id": 1066139428, "lat": 59.517075, "lon": -1.6412489}, {"type": "node", "id": 1066139429, "lat": 59.5150705, "lon": -1.6455606}, {"type": "node", "id": 1066139430, "lat": 59.5182611, "lon": -1.6406685}, {"type": "node", "id": 1066139432, "lat": 59.5169416, "lon": -1.6411}, {"type": "node", "id": 1066139434, "lat": 59.518207, "lon": -1.634184}, {"type": "node", "id": 1066139436, "lat": 59.5174316, "lon": -1.6405191}, {"type": "node", "id": 1066139438, "lat": 59.5172274, "lon": -1.6413562}, {"type": "node", "id": 1066139440, "lat": 59.5179114, "lon": -1.6408547}, {"type": "node", "id": 1066139442, "lat": 59.5230177, "lon": -1.6340177}, {"type": "node", "id": 1066139443, "lat": 59.5166614, "lon": -1.6404121}, {"type": "node", "id": 1066139444, "lat": 59.521992, "lon": -1.6331701}, {"type": "node", "id": 1066139445, "lat": 59.5230682, "lon": -1.6340393}, {"type": "node", "id": 1066139448, "lat": 59.5198256, "lon": -1.6395066}, {"type": "node", "id": 1066139450, "lat": 59.5194694, "lon": -1.6402837}, {"type": "node", "id": 1066139451, "lat": 59.5150562, "lon": -1.6460083}, {"type": "node", "id": 1066139452, "lat": 59.5175486, "lon": -1.6405553}, {"type": "node", "id": 1066139453, "lat": 59.5201328, "lon": -1.6399298}, {"type": "node", "id": 1066139455, "lat": 59.5199739, "lon": -1.6398097}, {"type": "node", "id": 1066139456, "lat": 59.5171811, "lon": -1.6413562}, {"type": "node", "id": 1066139457, "lat": 59.5160545, "lon": -1.6357933}, {"type": "node", "id": 1066139458, "lat": 59.5197091, "lon": -1.6334223}, {"type": "node", "id": 1066139459, "lat": 59.5199947, "lon": -1.64022}, {"type": "node", "id": 1066139460, "lat": 59.5173462, "lon": -1.6405687}, {"type": "node", "id": 1066139461, "lat": 59.5161157, "lon": -1.6433593}, {"type": "node", "id": 1066139462, "lat": 59.5169607, "lon": -1.6410715}, {"type": "node", "id": 1066139464, "lat": 59.5168764, "lon": -1.6409861}, {"type": "node", "id": 1066139465, "lat": 59.5223562, "lon": -1.6370491}, {"type": "node", "id": 1066139468, "lat": 59.5166097, "lon": -1.6352998}, {"type": "node", "id": 1066139470, "lat": 59.5222396, "lon": -1.6331862}, {"type": "node", "id": 1066139471, "lat": 59.5194887, "lon": -1.6332506}, {"type": "node", "id": 1066139472, "lat": 59.5221008, "lon": -1.633154}, {"type": "node", "id": 1066139473, "lat": 59.517309, "lon": -1.6416405}, {"type": "node", "id": 1066139474, "lat": 59.5189554, "lon": -1.6336422}, {"type": "node", "id": 1066139475, "lat": 59.5162858, "lon": -1.6376762}, {"type": "node", "id": 1066139477, "lat": 59.5200819, "lon": -1.6401541}, {"type": "node", "id": 1066139478, "lat": 59.5218804, "lon": -1.6331701}, {"type": "node", "id": 1066139479, "lat": 59.5176655, "lon": -1.6345863}, {"type": "node", "id": 1066139480, "lat": 59.5172546, "lon": -1.6413831}, {"type": "node", "id": 1066145353, "lat": 59.5243359, "lon": -1.6341398}, {"type": "node", "id": 1066145354, "lat": 59.5232231, "lon": -1.6338945}, {"type": "node", "id": 1066145356, "lat": 59.5243209, "lon": -1.6342269}, {"type": "node", "id": 1066145359, "lat": 59.524291, "lon": -1.6343449}, {"type": "node", "id": 1066145362, "lat": 59.5246733, "lon": -1.6346298}, {"type": "node", "id": 1066145363, "lat": 59.524389, "lon": -1.6343181}, {"type": "node", "id": 1066145365, "lat": 59.5242965, "lon": -1.6338529}, {"type": "node", "id": 1066145369, "lat": 59.522756, "lon": -1.6363117}, {"type": "node", "id": 1066145370, "lat": 59.5248089, "lon": -1.6347569}, {"type": "node", "id": 1066145372, "lat": 59.5229994, "lon": -1.6356}, {"type": "node", "id": 1066145373, "lat": 59.524204, "lon": -1.6344308}, {"type": "node", "id": 1066145374, "lat": 59.5240836, "lon": -1.6335069}, {"type": "node", "id": 1066145375, "lat": 59.5243584, "lon": -1.6340527}, {"type": "node", "id": 1066159008, "lat": 59.5282902, "lon": -1.636083}, {"type": "node", "id": 1066159010, "lat": 59.5277815, "lon": -1.6352783}, {"type": "node", "id": 1066159012, "lat": 59.5283419, "lon": -1.6361527}, {"type": "node", "id": 1066159030, "lat": 59.5280155, "lon": -1.6356699}, {"type": "node", "id": 1066159034, "lat": 59.5270307, "lon": -1.6341089}, {"type": "node", "id": 1066159037, "lat": 59.5269382, "lon": -1.6335456}, {"type": "node", "id": 1066159041, "lat": 59.5274387, "lon": -1.6347097}, {"type": "node", "id": 1066159044, "lat": 59.527874, "lon": -1.6354768}, {"type": "node", "id": 1066159046, "lat": 59.52767, "lon": -1.6349887}, {"type": "node", "id": 1066159047, "lat": 59.5268402, "lon": -1.6328912}, {"type": "node", "id": 1066159057, "lat": 59.5270742, "lon": -1.634243}, {"type": "node", "id": 1066159061, "lat": 59.5271422, "lon": -1.634361}, {"type": "node", "id": 1066159064, "lat": 59.5275693, "lon": -1.6348438}, {"type": "node", "id": 1066284934, "lat": 59.523606, "lon": -1.6397009}, {"type": "node", "id": 1066284957, "lat": 59.5227541, "lon": -1.6414306}, {"type": "node", "id": 1066284991, "lat": 59.5234188, "lon": -1.6401617}, {"type": "node", "id": 1066445965, "lat": 59.5397264, "lon": -1.615306}, {"type": "node", "id": 1066445968, "lat": 59.5377884, "lon": -1.6108907}, {"type": "node", "id": 1066445970, "lat": 59.5483826, "lon": -1.6109412}, {"type": "node", "id": 1066445972, "lat": 59.5398904, "lon": -1.615088}, {"type": "node", "id": 1066445973, "lat": 59.5344976, "lon": -1.6179213}, {"type": "node", "id": 1066445975, "lat": 59.5377081, "lon": -1.6036472}, {"type": "node", "id": 1066445996, "lat": 59.5389287, "lon": -1.6150262}, {"type": "node", "id": 1066446000, "lat": 59.5360126, "lon": -1.6097361}, {"type": "node", "id": 1066446004, "lat": 59.5351027, "lon": -1.6119449}, {"type": "node", "id": 1066446006, "lat": 59.5466062, "lon": -1.6136108}, {"type": "node", "id": 1066446009, "lat": 59.5405526, "lon": -1.6141872}, {"type": "node", "id": 1066446012, "lat": 59.5377843, "lon": -1.6037491, "tags": {"amenity": "ferry_terminal", "ferry": "yes", "public_transport": "station"}}, {"type": "node", "id": 1066446016, "lat": 59.5373378, "lon": -1.6039488}, {"type": "node", "id": 1066446017, "lat": 59.5401763, "lon": -1.6145806}, {"type": "node", "id": 1066446019, "lat": 59.5329693, "lon": -1.6199247}, {"type": "node", "id": 1066446023, "lat": 59.537371, "lon": -1.6095069}, {"type": "node", "id": 1066446024, "lat": 59.5403804, "lon": -1.6143099}, {"type": "node", "id": 1066446027, "lat": 59.5326559, "lon": -1.6230952}, {"type": "node", "id": 1066446029, "lat": 59.5333248, "lon": -1.6187183}, {"type": "node", "id": 1066446033, "lat": 59.5344151, "lon": -1.6179647}, {"type": "node", "id": 1066446052, "lat": 59.5519205, "lon": -1.6098619}, {"type": "node", "id": 1066446054, "lat": 59.5347276, "lon": -1.6176741}, {"type": "node", "id": 1066446055, "lat": 59.5481956, "lon": -1.6155864}, {"type": "node", "id": 1066446059, "lat": 59.5352267, "lon": -1.6135222}, {"type": "node", "id": 1066446060, "lat": 59.5351046, "lon": -1.6120813}, {"type": "node", "id": 1066446061, "lat": 59.5477699, "lon": -1.6152876}, {"type": "node", "id": 1066446064, "lat": 59.5418826, "lon": -1.6134819}, {"type": "node", "id": 1066446086, "lat": 59.5326833, "lon": -1.6228437}, {"type": "node", "id": 1066446090, "lat": 59.5434123, "lon": -1.6131345}, {"type": "node", "id": 1066446093, "lat": 59.5485538, "lon": -1.6146523}, {"type": "node", "id": 1066446094, "lat": 59.5364034, "lon": -1.6084863}, {"type": "node", "id": 1066446097, "lat": 59.5343191, "lon": -1.6179557}, {"type": "node", "id": 1066446099, "lat": 59.5378935, "lon": -1.6113005}, {"type": "node", "id": 1066446101, "lat": 59.5335246, "lon": -1.6183072}, {"type": "node", "id": 1066446116, "lat": 59.5351179, "lon": -1.6117427}, {"type": "node", "id": 1066446120, "lat": 59.5518743, "lon": -1.6099129}, {"type": "node", "id": 1066446122, "lat": 59.5319095, "lon": -1.6244181}, {"type": "node", "id": 1066446125, "lat": 59.5371347, "lon": -1.6071344}, {"type": "node", "id": 1066446129, "lat": 59.5519312, "lon": -1.6098619, "tags": {"barrier": "gate"}}, {"type": "node", "id": 1066446143, "lat": 59.5495273, "lon": -1.6094887}, {"type": "node", "id": 1066446146, "lat": 59.537068, "lon": -1.6074091}, {"type": "node", "id": 1066446160, "lat": 59.5338493, "lon": -1.6178742}, {"type": "node", "id": 1066446163, "lat": 59.5437694, "lon": -1.6129278}, {"type": "node", "id": 1066446166, "lat": 59.5356412, "lon": -1.6103661}, {"type": "node", "id": 1066446169, "lat": 59.5421791, "lon": -1.6135963}, {"type": "node", "id": 1066446172, "lat": 59.5428842, "lon": -1.6135206}, {"type": "node", "id": 1066446174, "lat": 59.5502624, "lon": -1.6091783}, {"type": "node", "id": 1066446176, "lat": 59.5350829, "lon": -1.6147376}, {"type": "node", "id": 1066446191, "lat": 59.5447693, "lon": -1.6121782}, {"type": "node", "id": 1066446192, "lat": 59.5377072, "lon": -1.6104986}, {"type": "node", "id": 1066446194, "lat": 59.5362981, "lon": -1.6087214}, {"type": "node", "id": 1066446198, "lat": 59.5483039, "lon": -1.6115072}, {"type": "node", "id": 1066446201, "lat": 59.5371226, "lon": -1.6093987}, {"type": "node", "id": 1066446208, "lat": 59.5374772, "lon": -1.6097026}, {"type": "node", "id": 1066446212, "lat": 59.53315, "lon": -1.6190836}, {"type": "node", "id": 1066446228, "lat": 59.5485146, "lon": -1.6152471}, {"type": "node", "id": 1066446235, "lat": 59.5330438, "lon": -1.6195087}, {"type": "node", "id": 1066446240, "lat": 59.5314433, "lon": -1.6262674}, {"type": "node", "id": 1066446246, "lat": 59.5370169, "lon": -1.6094305}, {"type": "node", "id": 1066446271, "lat": 59.5498522, "lon": -1.6092233}, {"type": "node", "id": 1066446276, "lat": 59.5480742, "lon": -1.6155484}, {"type": "node", "id": 1066446284, "lat": 59.543824, "lon": -1.6128412}, {"type": "node", "id": 1066446288, "lat": 59.5330015, "lon": -1.6197351}, {"type": "node", "id": 1066446295, "lat": 59.5324984, "lon": -1.6236192}, {"type": "node", "id": 1066446299, "lat": 59.5327399, "lon": -1.6218735}, {"type": "node", "id": 1066446303, "lat": 59.5372002, "lon": -1.6051829}, {"type": "node", "id": 1066446326, "lat": 59.5348924, "lon": -1.6171096}, {"type": "node", "id": 1066446327, "lat": 59.5316293, "lon": -1.6254482}, {"type": "node", "id": 1066446331, "lat": 59.5356561, "lon": -1.6104439}, {"type": "node", "id": 1066446340, "lat": 59.5431902, "lon": -1.6132757}, {"type": "node", "id": 1066446345, "lat": 59.5371693, "lon": -1.6045207}, {"type": "node", "id": 1066446351, "lat": 59.5521597, "lon": -1.6099209}, {"type": "node", "id": 1066446374, "lat": 59.5443108, "lon": -1.6120011}, {"type": "node", "id": 1066446377, "lat": 59.5356412, "lon": -1.6103255}, {"type": "node", "id": 1066446379, "lat": 59.5458324, "lon": -1.6127204}, {"type": "node", "id": 1066446384, "lat": 59.5356771, "lon": -1.6104816}, {"type": "node", "id": 1066446389, "lat": 59.5513862, "lon": -1.6108811}, {"type": "node", "id": 1066446393, "lat": 59.5377639, "lon": -1.6037116}, {"type": "node", "id": 1066446398, "lat": 59.5351184, "lon": -1.6123413}, {"type": "node", "id": 1066446434, "lat": 59.5499536, "lon": -1.6091783}, {"type": "node", "id": 1066446438, "lat": 59.548437, "lon": -1.6154894}, {"type": "node", "id": 1066446444, "lat": 59.5483772, "lon": -1.6124597}, {"type": "node", "id": 1066446450, "lat": 59.5484188, "lon": -1.6130821}, {"type": "node", "id": 1066446461, "lat": 59.5519885, "lon": -1.6098619}, {"type": "node", "id": 1066446466, "lat": 59.5484748, "lon": -1.6153893}, {"type": "node", "id": 1066446472, "lat": 59.5479071, "lon": -1.6154418}, {"type": "node", "id": 1066446501, "lat": 59.5371821, "lon": -1.6043787}, {"type": "node", "id": 1066446512, "lat": 59.5337834, "lon": -1.6179251}, {"type": "node", "id": 1066446515, "lat": 59.534837, "lon": -1.6173926}, {"type": "node", "id": 1066446520, "lat": 59.5376442, "lon": -1.6036472}, {"type": "node", "id": 1066446524, "lat": 59.5436758, "lon": -1.6129975}, {"type": "node", "id": 1066446527, "lat": 59.5394885, "lon": -1.615444}, {"type": "node", "id": 1066446553, "lat": 59.5325626, "lon": -1.6234655}, {"type": "node", "id": 1066446557, "lat": 59.535204, "lon": -1.6113633}, {"type": "node", "id": 1066446569, "lat": 59.5316988, "lon": -1.6248655}, {"type": "node", "id": 1066446574, "lat": 59.5417286, "lon": -1.6134481}, {"type": "node", "id": 1066446580, "lat": 59.5379874, "lon": -1.611645}, {"type": "node", "id": 1066446585, "lat": 59.5372305, "lon": -1.6064303}, {"type": "node", "id": 1066446588, "lat": 59.5371715, "lon": -1.60466}, {"type": "node", "id": 1066446616, "lat": 59.5341146, "lon": -1.6178527}, {"type": "node", "id": 1066446621, "lat": 59.5372612, "lon": -1.6040978}, {"type": "node", "id": 1066446629, "lat": 59.5502347, "lon": -1.6091526}, {"type": "node", "id": 1066446633, "lat": 59.5407782, "lon": -1.6140369}, {"type": "node", "id": 1066446636, "lat": 59.5483791, "lon": -1.6155486}, {"type": "node", "id": 1066446640, "lat": 59.541409, "lon": -1.6134597}, {"type": "node", "id": 1066446666, "lat": 59.5352095, "lon": -1.6130337}, {"type": "node", "id": 1066446668, "lat": 59.550304, "lon": -1.6092381}, {"type": "node", "id": 1066446674, "lat": 59.5316437, "lon": -1.6251094}, {"type": "node", "id": 1066446678, "lat": 59.5392385, "lon": -1.6154184}, {"type": "node", "id": 1066446683, "lat": 59.5365295, "lon": -1.6097893}, {"type": "node", "id": 1066446690, "lat": 59.5462991, "lon": -1.6131743}, {"type": "node", "id": 1066446693, "lat": 59.534058, "lon": -1.617834}, {"type": "node", "id": 1066446721, "lat": 59.5350565, "lon": -1.6150359}, {"type": "node", "id": 1066446727, "lat": 59.546995, "lon": -1.6142838}, {"type": "node", "id": 1066446729, "lat": 59.5368599, "lon": -1.6078902}, {"type": "node", "id": 1066446736, "lat": 59.5442156, "lon": -1.6120502}, {"type": "node", "id": 1066446740, "lat": 59.5356289, "lon": -1.6103458}, {"type": "node", "id": 1066446744, "lat": 59.5327788, "lon": -1.6215359}, {"type": "node", "id": 1066446760, "lat": 59.5352271, "lon": -1.6132206}, {"type": "node", "id": 1066446762, "lat": 59.5412952, "lon": -1.6135147}, {"type": "node", "id": 1066446765, "lat": 59.5483375, "lon": -1.6110295}, {"type": "node", "id": 1066446771, "lat": 59.538082, "lon": -1.6119369}, {"type": "node", "id": 1066446774, "lat": 59.5349883, "lon": -1.6161949}, {"type": "node", "id": 1066446797, "lat": 59.5390381, "lon": -1.6152219}, {"type": "node", "id": 1066446799, "lat": 59.534956, "lon": -1.6165657}, {"type": "node", "id": 1066446803, "lat": 59.5467997, "lon": -1.6139696}, {"type": "node", "id": 1066446807, "lat": 59.5375653, "lon": -1.6099631}, {"type": "node", "id": 1066446809, "lat": 59.5393488, "lon": -1.6154513}, {"type": "node", "id": 1066446814, "lat": 59.5426094, "lon": -1.6136099}, {"type": "node", "id": 1066446815, "lat": 59.5519626, "lon": -1.6104439}, {"type": "node", "id": 1066446837, "lat": 59.538203, "lon": -1.6123475}, {"type": "node", "id": 1066446841, "lat": 59.5485642, "lon": -1.6148307}, {"type": "node", "id": 1066446844, "lat": 59.5440594, "lon": -1.6122297}, {"type": "node", "id": 1066446847, "lat": 59.5440031, "lon": -1.6123433}, {"type": "node", "id": 1066446851, "lat": 59.5457126, "lon": -1.6126365}, {"type": "node", "id": 1066446853, "lat": 59.5372342, "lon": -1.606143}, {"type": "node", "id": 1066446855, "lat": 59.5517446, "lon": -1.6102753}, {"type": "node", "id": 1066446882, "lat": 59.5409892, "lon": -1.6138239}, {"type": "node", "id": 1066446891, "lat": 59.5514926, "lon": -1.6108186}, {"type": "node", "id": 1066446897, "lat": 59.5316039, "lon": -1.6256656}, {"type": "node", "id": 1066446908, "lat": 59.5412072, "lon": -1.6135789}, {"type": "node", "id": 1066446915, "lat": 59.5336073, "lon": -1.6181468}, {"type": "node", "id": 1066446918, "lat": 59.5350964, "lon": -1.6145937}, {"type": "node", "id": 1066446949, "lat": 59.5361251, "lon": -1.6094685}, {"type": "node", "id": 1066465122, "lat": 59.5513409, "lon": -1.6108882}, {"type": "node", "id": 1066465137, "lat": 59.551236, "lon": -1.6108457}, {"type": "node", "id": 1066514237, "lat": 59.5204071, "lon": -1.6420134}, {"type": "node", "id": 1066514298, "lat": 59.520845, "lon": -1.6437267}, {"type": "node", "id": 1066514303, "lat": 59.5203826, "lon": -1.6422682}, {"type": "node", "id": 1066514319, "lat": 59.5207581, "lon": -1.6431694}, {"type": "node", "id": 1066514335, "lat": 59.5231171, "lon": -1.6340232}, {"type": "node", "id": 1066514337, "lat": 59.5233279, "lon": -1.6337684}, {"type": "node", "id": 1066514341, "lat": 59.5208397, "lon": -1.6435959}, {"type": "node", "id": 1066514349, "lat": 59.5204098, "lon": -1.6420724}, {"type": "node", "id": 1066514378, "lat": 59.5203867, "lon": -1.6421958}, {"type": "node", "id": 1066529122, "lat": 59.5179173, "lon": -1.6463237}, {"type": "node", "id": 1066529128, "lat": 59.5177495, "lon": -1.6456053}, {"type": "node", "id": 1066529176, "lat": 59.5178724, "lon": -1.6459536}, {"type": "node", "id": 1066529251, "lat": 59.517973, "lon": -1.6465436}, {"type": "node", "id": 1066529334, "lat": 59.5178982, "lon": -1.6460904}, {"type": "node", "id": 1066529343, "lat": 59.5178139, "lon": -1.6457899, "tags": {"barrier": "gate"}}, {"type": "node", "id": 1415252713, "lat": 59.5307878, "lon": -1.6266661}, {"type": "node", "id": 1415252819, "lat": 59.5303651, "lon": -1.626604}, {"type": "node", "id": 2016338647, "lat": 59.5481241, "lon": -1.6266103}, {"type": "node", "id": 2016338648, "lat": 59.5401159, "lon": -1.6217281}, {"type": "node", "id": 2016338649, "lat": 59.5479566, "lon": -1.6259467}, {"type": "node", "id": 2016338650, "lat": 59.5385603, "lon": -1.6253974}, {"type": "node", "id": 2016338651, "lat": 59.5393762, "lon": -1.6240456}, {"type": "node", "id": 2016338652, "lat": 59.5375475, "lon": -1.6277277}, {"type": "node", "id": 2016338653, "lat": 59.5459349, "lon": -1.6233804}, {"type": "node", "id": 2016338654, "lat": 59.5406597, "lon": -1.6199471}, {"type": "node", "id": 2016338655, "lat": 59.5474357, "lon": -1.6246678}, {"type": "node", "id": 2016338656, "lat": 59.5415506, "lon": -1.6199815}, {"type": "node", "id": 2016338657, "lat": 59.5476304, "lon": -1.6251957}, {"type": "node", "id": 2016338658, "lat": 59.5467723, "lon": -1.6241528}, {"type": "node", "id": 2016338659, "lat": 59.5461948, "lon": -1.6239726}, {"type": "node", "id": 2016338660, "lat": 59.5471421, "lon": -1.6243031}, {"type": "node", "id": 2016338661, "lat": 59.539114, "lon": -1.6243588}, {"type": "node", "id": 2016338662, "lat": 59.5396905, "lon": -1.6228997}, {"type": "node", "id": 2016338663, "lat": 59.5444003, "lon": -1.6195952}, {"type": "node", "id": 2016338664, "lat": 59.5407467, "lon": -1.6197755}, {"type": "node", "id": 2016338665, "lat": 59.5374181, "lon": -1.627865}, {"type": "node", "id": 2016338667, "lat": 59.5459131, "lon": -1.6231443}, {"type": "node", "id": 2016338668, "lat": 59.5458903, "lon": -1.6228353}, {"type": "node", "id": 2016338669, "lat": 59.5457609, "lon": -1.6224792}, {"type": "node", "id": 2016338670, "lat": 59.539572, "lon": -1.6235091}, {"type": "node", "id": 2016338671, "lat": 59.54775, "lon": -1.6256034}, {"type": "node", "id": 2016338674, "lat": 59.5399636, "lon": -1.6221573}, {"type": "node", "id": 2016338675, "lat": 59.5383634, "lon": -1.6258394}, {"type": "node", "id": 2016338676, "lat": 59.5400713, "lon": -1.6218268}, {"type": "node", "id": 2016338677, "lat": 59.5377216, "lon": -1.6274487}, {"type": "node", "id": 2016338678, "lat": 59.5434116, "lon": -1.6196253}, {"type": "node", "id": 2016338679, "lat": 59.5448255, "lon": -1.6202476}, {"type": "node", "id": 2016338680, "lat": 59.5460099, "lon": -1.6237151}, {"type": "node", "id": 2016338681, "lat": 59.5455205, "lon": -1.6217839}, {"type": "node", "id": 2016338682, "lat": 59.5405825, "lon": -1.6201961}, {"type": "node", "id": 2016338683, "lat": 59.5419541, "lon": -1.6196897}, {"type": "node", "id": 2016338684, "lat": 59.5446069, "lon": -1.6198527}, {"type": "node", "id": 2016338685, "lat": 59.5381469, "lon": -1.6268351}, {"type": "node", "id": 2016338687, "lat": 59.5427797, "lon": -1.6193807}, {"type": "node", "id": 2016338688, "lat": 59.5403225, "lon": -1.6214277}, {"type": "node", "id": 2016338690, "lat": 59.5463482, "lon": -1.624067}, {"type": "node", "id": 2016338691, "lat": 59.5424425, "lon": -1.6196382}, {"type": "node", "id": 2016338692, "lat": 59.5417572, "lon": -1.6198098}, {"type": "node", "id": 2016338693, "lat": 59.5398222, "lon": -1.6225221}, {"type": "node", "id": 2016338694, "lat": 59.5453802, "lon": -1.6211488}, {"type": "node", "id": 2016338695, "lat": 59.5388203, "lon": -1.6248953}, {"type": "node", "id": 2016338696, "lat": 59.5413232, "lon": -1.6200544}, {"type": "node", "id": 2016338697, "lat": 59.5451409, "lon": -1.6206767}, {"type": "node", "id": 2016338698, "lat": 59.5410839, "lon": -1.6199471}, {"type": "node", "id": 2016338699, "lat": 59.5379729, "lon": -1.6273286}, {"type": "node", "id": 2016338700, "lat": 59.5382204, "lon": -1.6262411}, {"type": "node", "id": 2016338701, "lat": 59.5430309, "lon": -1.6194751}, {"type": "node", "id": 2016338702, "lat": 59.5381252, "lon": -1.6271784}, {"type": "node", "id": 2016338703, "lat": 59.5409415, "lon": -1.6197669}, {"type": "node", "id": 2016338704, "lat": 59.5404313, "lon": -1.6210844}, {"type": "node", "id": 2016338705, "lat": 59.5405064, "lon": -1.6205394}, {"type": "node", "id": 2016338706, "lat": 59.5436291, "lon": -1.6196897}, {"type": "node", "id": 2016338708, "lat": 59.5441175, "lon": -1.6195738}, {"type": "node", "id": 2408374706, "lat": 59.538495, "lon": -1.6146909}, {"type": "node", "id": 2408374708, "lat": 59.5385919, "lon": -1.6143515}, {"type": "node", "id": 2408374710, "lat": 59.538657, "lon": -1.6140763}, {"type": "node", "id": 2412429162, "lat": 59.5240646, "lon": -1.6343334}, {"type": "node", "id": 2412429165, "lat": 59.5230541, "lon": -1.6351913}, {"type": "node", "id": 2412442831, "lat": 59.523985, "lon": -1.6334264}, {"type": "node", "id": 2412448105, "lat": 59.5175969, "lon": -1.6425893}, {"type": "node", "id": 2412448107, "lat": 59.5175268, "lon": -1.6427671}, {"type": "node", "id": 2412448109, "lat": 59.5174506, "lon": -1.6418337}, {"type": "node", "id": 2412896945, "lat": 59.5376836, "lon": -1.6031932, "tags": {"leisure": "slipway"}}, {"type": "node", "id": 2412896946, "lat": 59.5380018, "lon": -1.6036874}, {"type": "node", "id": 2412897498, "lat": 59.5377665, "lon": -1.6052746}, {"type": "node", "id": 2412897500, "lat": 59.5374538, "lon": -1.605583, "tags": {"leisure": "slipway"}}, {"type": "node", "id": 2412898858, "lat": 59.552562, "lon": -1.6090967}, {"type": "node", "id": 2412898859, "lat": 59.552861, "lon": -1.6085764}, {"type": "node", "id": 2412898860, "lat": 59.5523051, "lon": -1.6097171}, {"type": "node", "id": 2412898861, "lat": 59.5533286, "lon": -1.6072353}, {"type": "node", "id": 2412898862, "lat": 59.5532919, "lon": -1.6074694}, {"type": "node", "id": 3006160451, "lat": 59.5140428, "lon": -1.6525066}, {"type": "node", "id": 3006160467, "lat": 59.5206934, "lon": -1.6392822}, {"type": "node", "id": 4081565895, "lat": 59.5372181, "lon": -1.6056817}, {"type": "node", "id": 4081565896, "lat": 59.5372986, "lon": -1.6056685}, {"type": "node", "id": 4081565897, "lat": 59.5373141, "lon": -1.6057202}, {"type": "node", "id": 4081565898, "lat": 59.5377408, "lon": -1.6036659}, {"type": "node", "id": 4081565899, "lat": 59.5378361, "lon": -1.60343}, {"type": "node", "id": 6564918190, "lat": 59.5334871, "lon": -1.6015658}, {"type": "node", "id": 6564918191, "lat": 59.5336394, "lon": -1.6016704}, {"type": "node", "id": 6564918192, "lat": 59.5337795, "lon": -1.6017884}, {"type": "node", "id": 6564918193, "lat": 59.5339903, "lon": -1.6020539}, {"type": "node", "id": 6564918194, "lat": 59.534027, "lon": -1.6022605}, {"type": "node", "id": 6564918195, "lat": 59.5343874, "lon": -1.6023409}, {"type": "node", "id": 6564918196, "lat": 59.5346471, "lon": -1.6023946}, {"type": "node", "id": 6564918197, "lat": 59.534896, "lon": -1.6022122}, {"type": "node", "id": 6564918198, "lat": 59.5351367, "lon": -1.6023061}, {"type": "node", "id": 6564918199, "lat": 59.5352319, "lon": -1.6024402}, {"type": "node", "id": 6564918200, "lat": 59.5354454, "lon": -1.6026548}, {"type": "node", "id": 6564918201, "lat": 59.5356738, "lon": -1.6028827}, {"type": "node", "id": 6564918202, "lat": 59.5359009, "lon": -1.6029042}, {"type": "node", "id": 6564918203, "lat": 59.5360192, "lon": -1.6029793}, {"type": "node", "id": 6564918204, "lat": 59.5361444, "lon": -1.6031456}, {"type": "node", "id": 6564918205, "lat": 59.536385, "lon": -1.6032556}, {"type": "node", "id": 6564918206, "lat": 59.5365469, "lon": -1.6034943}, {"type": "node", "id": 6564918207, "lat": 59.5367386, "lon": -1.6038108}, {"type": "node", "id": 6564918208, "lat": 59.5369467, "lon": -1.6039529}, {"type": "node", "id": 6564918209, "lat": 59.5371425, "lon": -1.6041648}, {"type": "node", "id": 7792113476, "lat": 59.5153238, "lon": -1.6445522}, {"type": "node", "id": 7792113482, "lat": 59.5244704, "lon": -1.6446218}, {"type": "node", "id": 7792113483, "lat": 59.5244979, "lon": -1.6453744}, {"type": "node", "id": 7792113484, "lat": 59.5244995, "lon": -1.6459516}, {"type": "node", "id": 7792136785, "lat": 59.5246922, "lon": -1.6465268}, {"type": "node", "id": 7792136786, "lat": 59.5248592, "lon": -1.6469767}, {"type": "node", "id": 7792136787, "lat": 59.5248478, "lon": -1.6475039}, {"type": "node", "id": 7792136788, "lat": 59.5245679, "lon": -1.6477075}, {"type": "node", "id": 7792136789, "lat": 59.5244268, "lon": -1.6473829}, {"type": "node", "id": 7792136790, "lat": 59.5241698, "lon": -1.6466327}, {"type": "node", "id": 7792136791, "lat": 59.5240913, "lon": -1.6459058}, {"type": "node", "id": 7792136792, "lat": 59.5233025, "lon": -1.6465162}, {"type": "node", "id": 7792136793, "lat": 59.5229641, "lon": -1.64689}, {"type": "node", "id": 7792136794, "lat": 59.5221183, "lon": -1.6475914}, {"type": "node", "id": 7792136795, "lat": 59.5215058, "lon": -1.6479825}, {"type": "node", "id": 7792136796, "lat": 59.5210275, "lon": -1.6489715}, {"type": "node", "id": 7792136797, "lat": 59.5204551, "lon": -1.6496826}, {"type": "node", "id": 7792136798, "lat": 59.5203029, "lon": -1.6499852}, {"type": "node", "id": 7792136799, "lat": 59.5202018, "lon": -1.6503626}, {"type": "node", "id": 7792136800, "lat": 59.5203949, "lon": -1.6510382}, {"type": "node", "id": 7792136801, "lat": 59.5207919, "lon": -1.6516614}, {"type": "node", "id": 7792136802, "lat": 59.5211626, "lon": -1.652059}, {"type": "node", "id": 7792136803, "lat": 59.5213421, "lon": -1.6524335}, {"type": "node", "id": 7792136804, "lat": 59.5214207, "lon": -1.6532107}, {"type": "node", "id": 7792136805, "lat": 59.5215625, "lon": -1.6538115}, {"type": "node", "id": 7792136806, "lat": 59.5215906, "lon": -1.6547899}, {"type": "node", "id": 7792136807, "lat": 59.5216936, "lon": -1.6551652}, {"type": "node", "id": 7792136808, "lat": 59.5218594, "lon": -1.6551886}, {"type": "node", "id": 7792136809, "lat": 59.5220761, "lon": -1.6551864}, {"type": "node", "id": 7792136810, "lat": 59.5222163, "lon": -1.6551849}, {"type": "node", "id": 7792136811, "lat": 59.5223443, "lon": -1.6553843}, {"type": "node", "id": 7792136812, "lat": 59.5223583, "lon": -1.6558359}, {"type": "node", "id": 7792136813, "lat": 59.5222194, "lon": -1.6563392}, {"type": "node", "id": 7792136814, "lat": 59.5220801, "lon": -1.6566919}, {"type": "node", "id": 7792136815, "lat": 59.5218123, "lon": -1.6566946}, {"type": "node", "id": 7792136816, "lat": 59.5215303, "lon": -1.6561203}, {"type": "node", "id": 7792136817, "lat": 59.5212998, "lon": -1.6557212}, {"type": "node", "id": 7792136818, "lat": 59.5210187, "lon": -1.6554982}, {"type": "node", "id": 7792136819, "lat": 59.5204951, "lon": -1.6551522}, {"type": "node", "id": 7792136820, "lat": 59.5197295, "lon": -1.6549595}, {"type": "node", "id": 7792136821, "lat": 59.5193332, "lon": -1.654537}, {"type": "node", "id": 7792136822, "lat": 59.5190641, "lon": -1.6540379}, {"type": "node", "id": 7792136823, "lat": 59.5188351, "lon": -1.6542158}, {"type": "node", "id": 7792136824, "lat": 59.518543, "lon": -1.6546454}, {"type": "node", "id": 7792136825, "lat": 59.518033, "lon": -1.6546506}, {"type": "node", "id": 7792136826, "lat": 59.5176738, "lon": -1.6538012}, {"type": "node", "id": 7792136827, "lat": 59.5175178, "lon": -1.6526738}, {"type": "node", "id": 7792136828, "lat": 59.517605, "lon": -1.6518699}, {"type": "node", "id": 7792136829, "lat": 59.5177944, "lon": -1.6511906}, {"type": "node", "id": 7792136830, "lat": 59.5175629, "lon": -1.6504403}, {"type": "node", "id": 7792136831, "lat": 59.5171934, "lon": -1.6505193}, {"type": "node", "id": 7792136832, "lat": 59.5166719, "lon": -1.6510014}, {"type": "node", "id": 7792136833, "lat": 59.5160728, "lon": -1.6510327}, {"type": "node", "id": 7792136834, "lat": 59.5152677, "lon": -1.6503637}, {"type": "node", "id": 7792136835, "lat": 59.514655, "lon": -1.6500939}, {"type": "node", "id": 7792136836, "lat": 59.5153251, "lon": -1.6432377}, {"type": "node", "id": 7792136837, "lat": 59.5151694, "lon": -1.642286}, {"type": "node", "id": 7792136838, "lat": 59.5147208, "lon": -1.6414127}, {"type": "node", "id": 7792136839, "lat": 59.5139554, "lon": -1.6412703}, {"type": "node", "id": 7792136840, "lat": 59.5135589, "lon": -1.6407978}, {"type": "node", "id": 7792136841, "lat": 59.5131612, "lon": -1.6398989}, {"type": "node", "id": 7792136842, "lat": 59.5128035, "lon": -1.6396519}, {"type": "node", "id": 7792136843, "lat": 59.5125585, "lon": -1.6386259}, {"type": "node", "id": 7792136844, "lat": 59.5125304, "lon": -1.637673}, {"type": "node", "id": 7792136845, "lat": 59.5127326, "lon": -1.6370437}, {"type": "node", "id": 7792136846, "lat": 59.5127804, "lon": -1.6358891}, {"type": "node", "id": 7792136847, "lat": 59.5129314, "lon": -1.6352102}, {"type": "node", "id": 7792136848, "lat": 59.5134156, "lon": -1.6351046}, {"type": "node", "id": 7792136849, "lat": 59.5136572, "lon": -1.634826}, {"type": "node", "id": 7792136850, "lat": 59.5137981, "lon": -1.6350754}, {"type": "node", "id": 7792136851, "lat": 59.5140534, "lon": -1.6351981}, {"type": "node", "id": 7792136852, "lat": 59.5143583, "lon": -1.6347933}, {"type": "node", "id": 7792136853, "lat": 59.5146503, "lon": -1.6343637}, {"type": "node", "id": 7792136854, "lat": 59.5147508, "lon": -1.6338106}, {"type": "node", "id": 7792136855, "lat": 59.5147612, "lon": -1.6329576}, {"type": "node", "id": 7792136856, "lat": 59.5148481, "lon": -1.6321538}, {"type": "node", "id": 7792136857, "lat": 59.5148582, "lon": -1.6312003}, {"type": "node", "id": 7792136858, "lat": 59.5149583, "lon": -1.6305219}, {"type": "node", "id": 7792136859, "lat": 59.515351, "lon": -1.6296395}, {"type": "node", "id": 7792136860, "lat": 59.5156046, "lon": -1.6291349}, {"type": "node", "id": 7792136861, "lat": 59.5159108, "lon": -1.6292068}, {"type": "node", "id": 7792136862, "lat": 59.516307, "lon": -1.6295787}, {"type": "node", "id": 7792136863, "lat": 59.5165, "lon": -1.6301537}, {"type": "node", "id": 7792136864, "lat": 59.5166427, "lon": -1.6310554}, {"type": "node", "id": 7792136865, "lat": 59.5168754, "lon": -1.6321818}, {"type": "node", "id": 7792136866, "lat": 59.5172974, "lon": -1.6326289}, {"type": "node", "id": 7792136867, "lat": 59.5179093, "lon": -1.6325972}, {"type": "node", "id": 7792136868, "lat": 59.5182893, "lon": -1.6317149}, {"type": "node", "id": 7792136869, "lat": 59.5182995, "lon": -1.6308114}, {"type": "node", "id": 7792136870, "lat": 59.5180549, "lon": -1.629961}, {"type": "node", "id": 7792136871, "lat": 59.5180901, "lon": -1.6289069}, {"type": "node", "id": 7792136872, "lat": 59.5184831, "lon": -1.6280745}, {"type": "node", "id": 7792136873, "lat": 59.5190159, "lon": -1.6271402}, {"type": "node", "id": 7792136874, "lat": 59.5196246, "lon": -1.6260044}, {"type": "node", "id": 7792136875, "lat": 59.5199176, "lon": -1.6259008}, {"type": "node", "id": 7792136876, "lat": 59.5202245, "lon": -1.6262236}, {"type": "node", "id": 7792136877, "lat": 59.520393, "lon": -1.6272004}, {"type": "node", "id": 7792136878, "lat": 59.5208411, "lon": -1.627873}, {"type": "node", "id": 7792136879, "lat": 59.5209837, "lon": -1.6286743}, {"type": "node", "id": 7792136880, "lat": 59.5211771, "lon": -1.629425}, {"type": "node", "id": 7792136881, "lat": 59.5214199, "lon": -1.6296482}, {"type": "node", "id": 7792136882, "lat": 59.5218538, "lon": -1.629794}, {"type": "node", "id": 7792136883, "lat": 59.5221713, "lon": -1.6293389}, {"type": "node", "id": 7792136884, "lat": 59.5225662, "lon": -1.6292091}, {"type": "node", "id": 7792136885, "lat": 59.5228353, "lon": -1.629708}, {"type": "node", "id": 7792136886, "lat": 59.5233326, "lon": -1.6297276}, {"type": "node", "id": 7792136887, "lat": 59.5239179, "lon": -1.6292947}, {"type": "node", "id": 7792136888, "lat": 59.524426, "lon": -1.6286367}, {"type": "node", "id": 7792136889, "lat": 59.5246683, "lon": -1.6286591}, {"type": "node", "id": 7792136890, "lat": 59.5250138, "lon": -1.6290818}, {"type": "node", "id": 7792136891, "lat": 59.5252557, "lon": -1.629004}, {"type": "node", "id": 7792136892, "lat": 59.5257394, "lon": -1.6286974}, {"type": "node", "id": 7792136893, "lat": 59.5259663, "lon": -1.6277915}, {"type": "node", "id": 7792136894, "lat": 59.5261439, "lon": -1.6274885}, {"type": "node", "id": 7792136895, "lat": 59.5264123, "lon": -1.6277365}, {"type": "node", "id": 7792136896, "lat": 59.5266671, "lon": -1.6276332}, {"type": "node", "id": 7792136897, "lat": 59.5271001, "lon": -1.6274527}, {"type": "node", "id": 7792136898, "lat": 59.5274795, "lon": -1.6263945}, {"type": "node", "id": 7792136899, "lat": 59.5278339, "lon": -1.625487}, {"type": "node", "id": 7792136900, "lat": 59.5277935, "lon": -1.6247094}, {"type": "node", "id": 7792136901, "lat": 59.5274475, "lon": -1.624136}, {"type": "node", "id": 7792136902, "lat": 59.5271913, "lon": -1.6236872}, {"type": "node", "id": 7792136903, "lat": 59.52697, "lon": -1.6221085}, {"type": "node", "id": 7792136904, "lat": 59.5270568, "lon": -1.6212542}, {"type": "node", "id": 7792136905, "lat": 59.5270165, "lon": -1.6205519}, {"type": "node", "id": 7792136906, "lat": 59.5266194, "lon": -1.6199039}, {"type": "node", "id": 7792136907, "lat": 59.5261969, "lon": -1.6193063}, {"type": "node", "id": 7792136908, "lat": 59.5258262, "lon": -1.6189841}, {"type": "node", "id": 7792136909, "lat": 59.5256841, "lon": -1.6183583}, {"type": "node", "id": 7792136910, "lat": 59.5260757, "lon": -1.6170741}, {"type": "node", "id": 7792136911, "lat": 59.5266444, "lon": -1.615361}, {"type": "node", "id": 7792136912, "lat": 59.5273142, "lon": -1.6133707}, {"type": "node", "id": 7792136913, "lat": 59.5277455, "lon": -1.6126127}, {"type": "node", "id": 7792136914, "lat": 59.5280767, "lon": -1.6125086}, {"type": "node", "id": 7792136915, "lat": 59.5283319, "lon": -1.6126059}, {"type": "node", "id": 7792136916, "lat": 59.5285114, "lon": -1.6129553}, {"type": "node", "id": 7792136917, "lat": 59.5287433, "lon": -1.6137308}, {"type": "node", "id": 7792136918, "lat": 59.5289622, "lon": -1.6144562}, {"type": "node", "id": 7792136919, "lat": 59.5293449, "lon": -1.614527}, {"type": "node", "id": 7792136920, "lat": 59.5295481, "lon": -1.6142486}, {"type": "node", "id": 7792136921, "lat": 59.5297234, "lon": -1.6131924}, {"type": "node", "id": 7792136922, "lat": 59.5299256, "lon": -1.6125877}, {"type": "node", "id": 7792136923, "lat": 59.5301668, "lon": -1.6122084}, {"type": "node", "id": 7792136924, "lat": 59.5304855, "lon": -1.6122048}, {"type": "node", "id": 7792136925, "lat": 59.5306279, "lon": -1.612931}, {"type": "node", "id": 7792136926, "lat": 59.5307962, "lon": -1.6138076}, {"type": "node", "id": 7792136927, "lat": 59.531181, "lon": -1.6145563}, {"type": "node", "id": 7792136928, "lat": 59.5316912, "lon": -1.6146508}, {"type": "node", "id": 7792136929, "lat": 59.5321664, "lon": -1.6158503}, {"type": "node", "id": 7792136930, "lat": 59.5321821, "lon": -1.6168541}, {"type": "node", "id": 7792136931, "lat": 59.5324261, "lon": -1.6174287}, {"type": "node", "id": 7792136932, "lat": 59.5325545, "lon": -1.6177537}, {"type": "node", "id": 7792136933, "lat": 59.5324801, "lon": -1.6184574}, {"type": "node", "id": 7792136934, "lat": 59.5324186, "lon": -1.6192362}, {"type": "node", "id": 7792136935, "lat": 59.5324831, "lon": -1.6195115}, {"type": "node", "id": 7792136936, "lat": 59.5325981, "lon": -1.6195856}, {"type": "node", "id": 7792136937, "lat": 59.5327513, "lon": -1.6196843}, {"type": "node", "id": 7792136938, "lat": 59.5329418, "lon": -1.6194059}, {"type": "node", "id": 7792136939, "lat": 59.5330803, "lon": -1.6188019}, {"type": "node", "id": 7792136940, "lat": 59.5334336, "lon": -1.6175178}, {"type": "node", "id": 7792136941, "lat": 59.5335184, "lon": -1.6160107}, {"type": "node", "id": 7792136942, "lat": 59.5339872, "lon": -1.6150012}, {"type": "node", "id": 7792136943, "lat": 59.534458, "lon": -1.6146946}, {"type": "node", "id": 7792136944, "lat": 59.5348532, "lon": -1.6146901}, {"type": "node", "id": 8094147153, "lat": 59.5181442, "lon": -1.6407307}, {"type": "node", "id": 8094147154, "lat": 59.5178519, "lon": -1.6399455}, {"type": "node", "id": 8630607678, "lat": 59.5142775, "lon": -1.6512594}, {"type": "node", "id": 8630607679, "lat": 59.5143681, "lon": -1.6510501}, {"type": "node", "id": 8630607680, "lat": 59.5144328, "lon": -1.6506264}, {"type": "node", "id": 8630607681, "lat": 59.516591, "lon": -1.642639}, {"type": "node", "id": 8630607682, "lat": 59.5166863, "lon": -1.6422473}, {"type": "node", "id": 8630607683, "lat": 59.5167094, "lon": -1.6418244}, {"type": "node", "id": 8630607684, "lat": 59.516727, "lon": -1.6416733}, {"type": "node", "id": 8630607685, "lat": 59.5168086, "lon": -1.6413726}, {"type": "node", "id": 8630607692, "lat": 59.5189976, "lon": -1.6401294}, {"type": "node", "id": 8630607693, "lat": 59.5190541, "lon": -1.6401302}, {"type": "node", "id": 8630607694, "lat": 59.5193682, "lon": -1.6402533}, {"type": "node", "id": 8630607695, "lat": 59.5196759, "lon": -1.6403138}, {"type": "node", "id": 8630607696, "lat": 59.522173, "lon": -1.6373348}, {"type": "node", "id": 8630607700, "lat": 59.5303247, "lon": -1.6266204}, {"type": "node", "id": 8630607701, "lat": 59.5304295, "lon": -1.6265878}, {"type": "node", "id": 8630607702, "lat": 59.533922, "lon": -1.6289268}, {"type": "node", "id": 8630607703, "lat": 59.5323221, "lon": -1.6291103}, {"type": "node", "id": 9085134764, "lat": 59.5216646, "lon": -1.6438045}, {"type": "node", "id": 9085134765, "lat": 59.5216197, "lon": -1.6436064}, {"type": "way", "id": 55395530, "nodes": [696004179, 1066095207, 1066094944], "tags": {"designation": "core_path", "foot": "designated", "highway": "unclassified"}}, {"type": "way", "id": 55396093, "nodes": [1066284991, 696005907, 1066094924, 1066284934, 696005909, 1066095114, 1066095147, 1066095022, 696005917, 696005920, 1066095173, 696005925, 1066094909, 1066095124, 1066095050, 696005929, 1066095046, 1066094936, 1066095028, 1066095177, 696005932, 696004275, 1066095154, 1066095188, 696005936, 1066095129, 696005940, 1066094949, 893420886, 1066048876, 696005943, 1066047661, 1066048474, 696005946, 696005950, 1066048438, 1066047732, 1066047575, 1066047572, 1066047688, 1066048565, 1066048729, 696005954, 8630607700, 1415252819, 8630607701, 1066047601, 1415252713, 1066048018, 696005962], "tags": {"designation": "core_path", "foot": "designated", "highway": "unclassified", "source": "bing", "surface": "paved"}}, {"type": "way", "id": 55396672, "nodes": [696007436, 1066446384, 893422484, 1066446683, 696007438, 1066446246, 1066446201, 696007442, 1066446023, 696007443, 1066446208, 1066446807, 1066446192, 1066445968, 1066446099, 1066446580, 1066446771, 1066446837, 2408374710, 696007452, 1066445996, 1066446797, 696007454, 1066446678, 1066446809, 1066446527, 696007457, 1066445965, 1066445972, 696007459, 1066446017, 696007462, 1066446024, 1066446009, 1066446633, 1066446882, 1066446908, 1066446762, 1066446640, 696007465, 1066446574, 1066446064, 1066446169, 696007468, 1066446814, 1066446172, 1066446340, 1066446090, 1066446524, 1066446163, 1066446284, 696007473, 1066446847, 1066446844, 696007476, 1066446736, 1066446374, 696007478, 1066446191, 1066446851, 1066446379, 696007481, 1066446690, 696007483, 1066446006, 1066446803, 1066446727, 696007485, 1066446061, 1066446472, 696007487, 1066446276, 1066446055, 696007490, 1066446636, 1066446438, 1066446466, 1066446228, 696007493, 1066446841, 1066446093, 696007496, 1066446450, 1066446444, 1066446198, 696007498, 696007503, 1066446765, 1066445970, 1066446143, 696007505, 1066446271, 1066446434, 696007507, 1066446629, 1066446174, 1066446668, 696007509, 696007512, 1066465137, 696007514, 1066465122, 1066446389, 1066446891, 696007517, 696007520, 1066446855, 1066446120, 1066446052, 1066446129], "tags": {"highway": "unclassified", "source": "Bing"}}, {"type": "way", "id": 55396826, "nodes": [1066446012, 1066446393, 4081565898, 1066445975, 1066446520, 696007842, 696007845, 1066446016, 1066446621, 696007849, 1066446501, 1066446345, 1066446588, 1066446303, 4081565895, 696007853, 1066446853, 1066446585, 696007856, 1066446125, 1066446146, 696007859, 1066446729, 696007863, 1066446094, 696007866, 1066446194, 893422627, 1066446949, 696007870, 1066446000, 696007873, 1066446377, 1066446740, 696007436], "tags": {"designation": "core_path", "foot": "designated", "highway": "unclassified", "source": "bing"}}, {"type": "way", "id": 75679675, "nodes": [893419435, 1066095110, 893419437, 696005886], "tags": {"highway": "service", "source": "os_opendata_streetview"}}, {"type": "way", "id": 75679690, "nodes": [893419595, 1066139448, 1066139455, 893419596, 1066139453, 1066139421, 893419598], "tags": {"highway": "track", "source": "Bing"}}, {"type": "way", "id": 75679703, "nodes": [893419839, 696004225], "tags": {"highway": "track", "source": "os_opendata_streetview"}}, {"type": "way", "id": 75679788, "nodes": [893420882, 893420886], "tags": {"highway": "service", "service": "driveway", "source": "os_opendata_streetview"}}, {"type": "way", "id": 75680081, "nodes": [1066048804, 1066048495, 1066048398, 1066048307, 893422146], "tags": {"highway": "track", "source": "os_opendata_streetview"}}, {"type": "way", "id": 75680159, "nodes": [893422274, 893422277, 893422280, 893422283, 893422285, 2016338647, 893422287, 893422288, 893422289, 1066048719, 893422290, 1066048759, 1066048219, 1066048126, 1066048832, 893422291, 1066048677, 1066048766, 893422292, 1066048795, 893422294, 1066048199, 1066048502, 1066047568, 1066048147, 893422296, 1066048653, 1066048041, 893422297, 1066047786, 1066048732, 1066047818, 1066048589, 1066048350, 1066048333, 893422146], "tags": {"highway": "track", "source": "os_opendata_streetview", "surface": "unpaved"}}, {"type": "way", "id": 75680319, "nodes": [893422351, 893422627], "tags": {"highway": "track", "source": "os_opendata_streetview", "surface": "unpaved"}}, {"type": "way", "id": 75680482, "nodes": [893423543, 1066115153, 8630607680, 893423545, 1066115090, 893423550, 1066115107, 893423554, 1066095009, 893423560, 696004179], "tags": {"designation": "core_path", "foot": "designated", "highway": "service", "source": "os_opendata_streetview"}}, {"type": "way", "id": 91737607, "nodes": [1066048565, 1066048618, 1066048346, 1066047609, 1066047572], "tags": {"highway": "track", "surface": "unpaved"}}, {"type": "way", "id": 91737615, "nodes": [893422146, 1066047927, 1066047608, 1066048691, 1066047972, 1066047967, 893422148, 1066048008, 1066047785, 1066047846, 893422152, 1066048079, 1066048834, 1066048149, 1066047959, 893422154, 1066048076, 893422157, 1066048671, 1066048468, 1066048304, 1066048010, 893422159, 1066047987, 1066048110, 1066047920, 1066048528, 1066048842, 893422160, 1066048867, 893422162, 1066048519, 1066047922, 1066048693, 1066047819, 1066048840, 893422165, 1066048421, 1066048592, 893422169, 1066048620, 1066047571, 1066048435, 1066048663, 1066048861, 893422170, 1066048338, 1066048015, 1066048253, 1066048720, 893422172, 1066048871, 893422173, 1066048019, 1066048043, 1066047548, 893422175, 1066048558, 1066048380, 1066048443, 893422177, 1066047566, 1066048622, 1066047542, 893422179, 1066047651, 1066048501, 1066047704, 893422181, 1066048525, 1066047834, 1066048360, 893422183, 1066047615, 1066048354, 1066048692, 1066047752, 893422185, 1066047872, 1066048143, 1066048189, 1066047528, 1066047816, 893422188, 1066047603, 1066047978, 1066047983, 893422189, 1066048762, 893422190, 1066048585, 1066047843, 893422191, 1066048160, 1066048012, 893422192, 1066048516, 1066048681, 1066048084, 1066047790, 1066047692, 1066047969, 1066047544, 893422194, 1066048714, 1066047902, 1066048039, 1066048665, 1066047974, 1066047930, 1066048697, 893422196, 1066048109, 1066047891, 1066047842, 1066048430, 893422197, 1066048726, 1066048212, 1066048722, 893422199, 1066047944, 1066047726, 1066047985, 893422201, 1066048611, 1066048121, 1066047866, 1066048756, 1066047925], "tags": {"highway": "track", "source": "OS_OpenData_StreetView"}}, {"type": "way", "id": 91737630, "nodes": [1066048157, 1066048395, 1066048445, 1066048410, 1066048194, 1066048536, 1066048310, 1066048078, 1066048242, 1066048415, 1066048401, 1066047613, 1066048292, 1066047567, 1066048717, 1066047839, 1066048206, 1066047697, 1066048680, 1066048492, 1066048217, 1066048644, 1066048801, 1066048250], "tags": {"highway": "track"}}, {"type": "way", "id": 91737644, "nodes": [1066048838, 1066048300, 1066048389, 1066047647, 1066048117, 1066047565, 1066048787, 1066047732], "tags": {"highway": "track", "source": "Bing"}}, {"type": "way", "id": 91741374, "nodes": [1066094947, 1066095158, 1066095050], "tags": {"highway": "track", "source": "Bing"}}, {"type": "way", "id": 91741378, "nodes": [696004184, 696004185, 1066095144, 1066095211], "tags": {"highway": "unclassified"}}, {"type": "way", "id": 91741381, "nodes": [1066095046, 1066095214, 1066095157, 1066095158], "tags": {"highway": "track", "source": "Bing"}}, {"type": "way", "id": 91741384, "nodes": [696004192, 1066139426, 1066139461, 696004193, 8630607681, 696004196, 1066139411, 8630607682, 1066139423, 8630607683, 8630607684, 1066139386, 8630607685, 696004198, 1066139387, 1066139432, 1066139462, 696004202, 1066139460, 1066139436, 696004206, 1066139452, 1066139403, 1066139394, 696004210, 1066139440, 8094147153, 1066139430, 1066139425, 696004212, 696004215, 696004216, 8630607692, 8630607693, 8630607694, 1066139450, 1066139408, 8630607695, 696004219, 1066139459, 1066139477, 696004221, 893419598, 3006160467, 696004225, 8630607696, 1066139465, 696004227, 1066145369, 1066139409, 1066145372, 696004232, 2412429165, 696004235, 696004238, 1066145354, 1066514337, 696004240, 696004242, 2412442831, 1066145374, 696004246, 1066145365, 1066145375, 696004267, 1066145362, 1066145370, 696004271, 696004275], "tags": {"highway": "unclassified"}}, {"type": "way", "id": 91741385, "nodes": [1066095123, 1066094900, 1066095064, 1066095042, 696005869], "tags": {"highway": "track", "source": "Bing"}}, {"type": "way", "id": 91742402, "nodes": [1066115130, 1066114972, 1066114975, 1066115072, 893423560], "tags": {"highway": "track", "source": "Bing"}}, {"type": "way", "id": 91744745, "nodes": [1066139434, 1066139479, 1066139468, 1066139393, 1066139457, 1066139475, 1066139443, 1066139404, 1066139464, 1066139432], "tags": {"highway": "residential", "source": "Bing"}}, {"type": "way", "id": 91744746, "nodes": [696004238, 1066514335, 1066139445, 1066139442, 1066139420, 1066139470, 1066139472, 1066139444, 1066139478, 1066139427, 1066139401, 1066139416, 1066139413, 1066139458, 1066139407, 1066139406, 1066139471, 1066139422, 1066139474, 1066139434], "tags": {"highway": "track", "source": "Bing"}}, {"type": "way", "id": 91744749, "nodes": [1066139397, 1066139473, 1066139399, 1066139480, 1066139438, 1066139456, 1066139385, 1066139428, 1066139462], "tags": {"highway": "path", "source": "Bing"}}, {"type": "way", "id": 91745527, "nodes": [696004267, 1066145363, 1066145359, 1066145373], "tags": {"highway": "service", "source": "Bing"}}, {"type": "way", "id": 91745528, "nodes": [1066145359, 1066145356, 1066145353, 1066145375], "tags": {"highway": "service", "source": "Bing"}}, {"type": "way", "id": 91747114, "nodes": [893420886, 1066159047, 1066159037, 1066159034, 1066159057, 1066159061, 1066159041, 1066159064, 1066159046, 1066159010, 1066159044, 1066159030, 1066159008, 1066159012], "tags": {"highway": "track", "source": "Bing", "surface": "grass"}}, {"type": "way", "id": 91764696, "nodes": [1066446815, 1066446855], "tags": {"highway": "service", "source": "Bing"}}, {"type": "way", "id": 91764699, "nodes": [1066446384, 1066446331, 1066446166, 1066446377], "tags": {"highway": "unclassified"}}, {"type": "way", "id": 91764700, "nodes": [1066446129, 1066446461, 1066446351], "tags": {"access": "private", "highway": "unclassified"}}, {"type": "way", "id": 91771582, "nodes": [1066514237, 1066514349, 1066514378, 1066514303, 893419435], "tags": {"highway": "path"}}, {"type": "way", "id": 91771600, "nodes": [1066514319, 1066514341, 1066514298], "tags": {"highway": "track"}}, {"type": "way", "id": 91774794, "nodes": [1066529251, 1066529122, 1066529334, 1066529176, 1066529343, 1066529128], "tags": {"highway": "track"}}, {"type": "way", "id": 191048479, "nodes": [1066048762, 2016338665, 2016338652, 2016338677, 2016338699, 2016338702, 2016338685, 2016338700, 2016338675, 2016338650, 2016338695, 2016338661, 2016338651, 2016338670, 2016338662, 2016338693, 2016338674, 2016338676, 2016338648, 2016338688, 2016338704, 2016338705, 2016338682, 2016338654, 2016338664, 2016338703, 2016338698, 2016338696, 2016338656, 2016338692, 2016338683, 2016338691, 2016338687, 2016338701, 2016338678, 2016338706, 2016338708, 2016338663, 2016338684, 2016338679, 2016338697, 2016338694, 2016338681, 2016338669, 2016338668, 2016338667, 2016338653, 2016338680, 2016338659, 2016338690], "tags": {"highway": "track"}}, {"type": "way", "id": 191048480, "nodes": [2016338658, 2016338660, 2016338655, 2016338657, 2016338671, 2016338649, 2016338647], "tags": {"highway": "track"}}, {"type": "way", "id": 232492864, "nodes": [2408374710, 2408374708, 2408374706], "tags": {"highway": "track"}}, {"type": "way", "id": 232924685, "nodes": [1066094936, 2412429162], "tags": {"highway": "footway"}}, {"type": "way", "id": 232926571, "nodes": [2412448107, 2412448105, 2412448109, 1066139397], "tags": {"highway": "footway"}}, {"type": "way", "id": 232965103, "nodes": [1066047925, 893422202, 893422204, 1066048466, 1066047569, 1066048050, 8630607702, 1066048675, 1066048119, 696005993], "tags": {"highway": "unclassified", "source": "OS_OpenData_StreetView"}}, {"type": "way", "id": 232968325, "nodes": [2412896946, 4081565899, 2412896945], "tags": {"highway": "service"}}, {"type": "way", "id": 232968328, "nodes": [2412897500, 2412897498], "tags": {"highway": "service"}}, {"type": "way", "id": 232968570, "nodes": [2412898860, 2412898858, 2412898859, 2412898862, 2412898861], "tags": {"highway": "footway"}}, {"type": "way", "id": 406030461, "nodes": [4081565898, 4081565899], "tags": {"highway": "service"}}, {"type": "way", "id": 406030463, "nodes": [4081565895, 4081565896, 4081565897, 2412897500], "tags": {"highway": "service"}}, {"type": "way", "id": 699102671, "nodes": [1066446501, 6564918209, 6564918208, 6564918207, 6564918206, 6564918205, 6564918204, 6564918203, 6564918202, 6564918201, 6564918200, 6564918199, 6564918198, 6564918197, 6564918196, 6564918195, 6564918194, 6564918193, 6564918192, 6564918191, 6564918190], "tags": {"highway": "path", "name": "To Puffin Rookery"}}, {"type": "way", "id": 834736048, "nodes": [1066446176, 1066446918, 696007424, 1066446059, 696007427, 1066446760, 1066446666, 696007430, 1066446398, 1066446060, 1066446004, 1066446116, 696007433, 1066446557, 696007436], "tags": {"designation": "core_path", "foot": "designated", "highway": "unclassified", "source": "bing"}}, {"type": "way", "id": 834736049, "nodes": [1066094944, 1066095189, 1066095222, 1066095211, 1066139451, 696004189, 1066139429, 1066139391, 7792113476, 696004192], "tags": {"designation": "core_path", "foot": "designated", "highway": "unclassified"}}, {"type": "way", "id": 834736050, "nodes": [1066094944, 696004184], "tags": {"highway": "unclassified"}}, {"type": "way", "id": 834736051, "nodes": [696005962, 1066047958, 696005969, 1066048250, 8630607703], "tags": {"highway": "unclassified", "surface": "paved"}}, {"type": "way", "id": 834736052, "nodes": [696005962, 1066446240, 696007399, 1066446897, 1066446327, 1066446674, 696007402, 1066446569, 1066446122, 696007404, 1066446295, 1066446553, 696007405, 1066446027, 1066446086, 696007407, 1066446299, 1066446744, 1066446019, 1066446288, 1066446235, 696007410, 1066446212, 1066446029, 1066446101, 1066446915, 696007412, 1066446512, 1066446160, 696007414, 1066446693, 1066446616, 1066446097, 1066446033, 1066445973, 696007416, 1066446054, 696007419, 1066446515, 1066446326, 1066446799, 1066446774, 696007422, 1066446721, 1066446176], "tags": {"designation": "core_path", "foot": "designated", "highway": "unclassified", "source": "bing"}}, {"type": "way", "id": 834736057, "nodes": [696004184, 696005861, 1066095005, 1066094977, 696005864, 1066095087, 1066095229, 1066095150, 1066095026, 696005866, 1066094961, 1066529128, 1066095153, 696005869, 1066095092, 1066095179, 696005872, 1066095131, 1066095029, 1066095001, 1066095020, 696005877, 1066094954, 696005882, 1066095146, 696005886, 1066095073, 696005890, 1066094979, 1066514298, 1066095012, 1066095218, 1066094905, 696005893, 1066094981, 696005895, 9085134765, 1066094933, 1066094976, 1066095076, 696005898, 696005900, 1066094926, 696005902, 1066095085, 1066094903, 1066095206, 1066284957, 696005905, 1066095145, 1066095117, 1066095041, 1066284991], "tags": {"highway": "unclassified", "surface": "paved"}}, {"type": "way", "id": 834736058, "nodes": [3006160451, 893423540, 1066115000, 893423541, 1066115083, 8630607678, 893423542, 8630607679, 893423543], "tags": {"highway": "service", "source": "os_opendata_streetview"}}, {"type": "way", "id": 834736059, "nodes": [893423543, 7792136835, 7792136834, 7792136833, 7792136832, 7792136831, 7792136830, 7792136829, 7792136828, 7792136827, 7792136826, 7792136825, 7792136824, 7792136823, 7792136822, 7792136821, 7792136820, 7792136819, 7792136818, 7792136817, 7792136816, 7792136815, 7792136814, 7792136813, 7792136812, 7792136811, 7792136810, 7792136809, 7792136808, 7792136807, 7792136806, 7792136805, 7792136804, 7792136803, 7792136802, 7792136801, 7792136800, 7792136799, 7792136798, 7792136797, 7792136796, 7792136795, 7792136794, 7792136793, 7792136792, 7792136791, 7792136790, 7792136789, 7792136788, 7792136787, 7792136786, 7792136785, 7792113484, 7792113483, 7792113482, 1066284991], "tags": {"designation": "core_path", "foot": "designated", "highway": "path", "source": "Shetland Islands Council"}}, {"type": "way", "id": 834736060, "nodes": [1066446176, 7792136944, 7792136943, 7792136942, 7792136941, 7792136940, 7792136939, 7792136938, 7792136937, 7792136936, 7792136935, 7792136934, 7792136933, 7792136932, 7792136931, 7792136930, 7792136929, 7792136928, 7792136927, 7792136926, 7792136925, 7792136924, 7792136923, 7792136922, 7792136921, 7792136920, 7792136919, 7792136918, 7792136917, 7792136916, 7792136915, 7792136914, 7792136913, 7792136912, 7792136911, 7792136910, 7792136909, 7792136908, 7792136907, 7792136906, 7792136905, 7792136904, 7792136903, 7792136902, 7792136901, 7792136900, 7792136899, 7792136898, 7792136897, 7792136896, 7792136895, 7792136894, 7792136893, 7792136892, 7792136891, 7792136890, 7792136889, 7792136888, 7792136887, 7792136886, 7792136885, 7792136884, 7792136883, 7792136882, 7792136881, 7792136880, 7792136879, 7792136878, 7792136877, 7792136876, 7792136875, 7792136874, 7792136873, 7792136872, 7792136871, 7792136870, 7792136869, 7792136868, 7792136867, 7792136866, 7792136865, 7792136864, 7792136863, 7792136862, 7792136861, 7792136860, 7792136859, 7792136858, 7792136857, 7792136856, 7792136855, 7792136854, 7792136853, 7792136852, 7792136851, 7792136850, 7792136849, 7792136848, 7792136847, 7792136846, 7792136845, 7792136844, 7792136843, 7792136842, 7792136841, 7792136840, 7792136839, 7792136838, 7792136837, 7792136836, 696004192], "tags": {"designation": "core_path", "foot": "designated", "highway": "path", "source": "Shetland Islands Council"}}, {"type": "way", "id": 868372346, "nodes": [8094147154, 8094147153], "tags": {"highway": "service"}}, {"type": "way", "id": 930836346, "nodes": [696005976, 1066048075, 1066048584, 1066048357, 696005980, 696005982, 1066048112, 1066048465, 696005986, 1066048155, 1066048478, 1066048562, 696005990, 1066047850, 696005993], "tags": {"highway": "unclassified", "surface": "paved"}}, {"type": "way", "id": 930836347, "nodes": [8630607703, 696005976], "tags": {"bridge": "yes", "highway": "unclassified", "layer": "1", "surface": "paved"}}, {"type": "way", "id": 982358259, "nodes": [9085134764, 9085134765], "tags": {"highway": "track"}}]}